Workbook

Sheet Dashboard
A1: Cidy Quality Tracker
C3: Found Answer Global | G3: Found Answer per topic area | M3: Found Answer per path
C4: Yes | D4: =COUNTIF('Test Cases'!F:F,"Yes")/COUNTA('Test Cases'!F:F) -> 0.40983607 | H4: Tester | I4: Yes | J4: No | K4: Not tested | N4: Yes | O4: No | P4: Not Tested
C5: No | D5: =COUNTIF('Test Cases'!F:F,"No")/COUNTA('Test Cases'!F:F) -> 0.57377049 | G5: {=_xlfn._xlws.SORT(_xlfn.UNIQUE(_xlfn._xlws.FILTER('Test Cases'!B2:B1000,'Test Cases'!B2:B1000<>"")))} -> About Cidy | I5: {=_xlfn.MAP(_xlfn.ANCHORARRAY(G5),_xlfn.LAMBDA(_xlpm.topic, _xlfn.LET( _xlpm.topics,'Test Cases'!B2:B1000, _xlpm.answers,'Test Cases'!F2:F1000, _xlpm.denom,COUNTIF(_xlpm.topics,_xlpm.topic), IFERROR(SUM((_xlpm.topics=_xlpm.topic)*(_xlpm.answers="Yes"))/_xlpm.denom,"") ) ))} -> 0.18181818 | J5: {=_xlfn.MAP(_xlfn.ANCHORARRAY(G5),_xlfn.LAMBDA(_xlpm.topic, _xlfn.LET( _xlpm.topics,'Test Cases'!B2:B1000, _xlpm.answers,'Test Cases'!F2:F1000, _xlpm.denom,COUNTIF(_xlpm.topics,_xlpm.topic), IFERROR(SUM((_xlpm.topics=_xlpm.topic)*(_xlpm.answers="No"))/_xlpm.denom,"") ) ))} -> 0.45454545 | K5: {=_xlfn.MAP(_xlfn.ANCHORARRAY(G5),_xlfn.LAMBDA(_xlpm.topic, _xlfn.LET( _xlpm.topics,'Test Cases'!B2:B1000, _xlpm.answers,'Test Cases'!F2:F1000, _xlpm.denom,COUNTIF(_xlpm.topics,_xlpm.topic), IFERROR(SUM((_xlpm.topics=_xlpm.topic)*(_xlpm.answers=""))/_xlpm.denom,"") ) ))} -> 0.36363636 | M5: {=_xlfn.LET( _xlpm.src,_xlfn._xlws.FILTER('Test Cases'!A2:A1000,ISNUMBER(SEARCH("-",'Test Cases'!A2:A1000))), _xlpm.paths,_xlfn.MAP(_xlpm.src,_xlfn.LAMBDA(_xlpm.x,TRIM(_xlfn.TEXTBEFORE(_xlpm.x,"-")))), _xlfn._xlws.SORT(_xlfn.UNIQUE(_xlpm.paths)) )} -> Clarification path | N5: {=_xlfn.MAP(_xlfn.ANCHORARRAY(M5),_xlfn.LAMBDA(_xlpm.path, _xlfn.LET( _xlpm.src,_xlfn._xlws.FILTER('Test Cases'!A2:F1000,ISNUMBER(SEARCH("-",'Test Cases'!A2:A1000))), _xlpm.paths,_xlfn.MAP(INDEX(_xlpm.src,,1),_xlfn.LAMBDA(_xlpm.x,TRIM(_xlfn.TEXTBEFORE(_xlpm.x,"-")))), _xlpm.answers,INDEX(_xlpm.src,,6), _xlpm.denom,SUM(--(_xlpm.paths=_xlpm.path)), IFERROR(SUM((_xlpm.paths=_xlpm.path)*(_xlpm.answers="Yes"))/_xlpm.denom,"") ) ))} -> 0.052631579 | O5: {=_xlfn.MAP(_xlfn.ANCHORARRAY(M5),_xlfn.LAMBDA(_xlpm.path, _xlfn.LET( _xlpm.src,_xlfn._xlws.FILTER('Test Cases'!A2:F1000,ISNUMBER(SEARCH("-",'Test Cases'!A2:A1000))), _xlpm.paths,_xlfn.MAP(INDEX(_xlpm.src,,1),_xlfn.LAMBDA(_xlpm.x,TRIM(_xlfn.TEXTBEFORE(_xlpm.x,"-")))), _xlpm.answers,INDEX(_xlpm.src,,6), _xlpm.denom,SUM(--(_xlpm.paths=_xlpm.path)), IFERROR(SUM((_xlpm.paths=_xlpm.path)*(_xlpm.answers="No"))/_xlpm.denom,"") ) ))} -> 0.052631579 | P5: {=_xlfn.MAP(_xlfn.ANCHORARRAY(M5),_xlfn.LAMBDA(_xlpm.path, _xlfn.LET( _xlpm.src,_xlfn._xlws.FILTER('Test Cases'!A2:F1000,ISNUMBER(SEARCH("-",'Test Cases'!A2:A1000))), _xlpm.paths,_xlfn.MAP(INDEX(_xlpm.src,,1),_xlfn.LAMBDA(_xlpm.x,TRIM(_xlfn.TEXTBEFORE(_xlpm.x,"-")))), _xlpm.answers,INDEX(_xlpm.src,,6), _xlpm.denom,SUM(--(_xlpm.paths=_xlpm.path)), IFERROR(SUM((_xlpm.paths=_xlpm.path)*(_xlpm.answers=""))/_xlpm.denom,"") ) ))} -> 0.89473684
C6: Not Tested | D6: =COUNTBLANK('Test Cases'!F2:F101)/ROWS('Test Cases'!F2:F101) -> 0.4 | G6: Country Data | H6: Ronen | I6: 0 | J6: 0 | K6: 1 | M6: Exit Cidy flow command | N6: 0 | O6: 0 | P6: 1
G7: DA | H7: Jack | I7: 0.81818182 | J7: 0.18181818 | K7: 0 | M7: Greeting guard | N7: 1 | O7: 0 | P7: 0
G8: Evaluation | I8: 0.14285714 | J8: 0.71428571 | K8: 0.14285714 | M8: Greeting path | N8: 0 | O8: 0 | P8: 1
G9: Exit Flow | I9: 0 | J9: 0 | K9: 1 | M9: Happy path | N9: 0.26984127 | O9: 0.52380952 | P9: 0.20634921
G10: Greeting | I10: 0.33333333 | J10: 0 | K10: 0.66666667 | M10: Out of scope | N10: 1 | O10: 0 | P10: 0
G11: Not Sure | I11: 0.047619048 | J11: 0.047619048 | K11: 0.9047619 | M11: Regression | N11: 0 | O11: 0 | P11: 1
G12: OOS | I12: 1 | J12: 0 | K12: 0 | M12: Vague path | N12: 0.2 | O12: 0.2 | P12: 0.6
G13: PD | H13: Jon | I13: 0.28571429 | J13: 0.64285714 | K13: 0.071428571
G14: PDF | I14: 0 | J14: 0.5 | K14: 0.5
G15: RPTC | I15: 0.11111111 | J15: 0.66666667 | K15: 0.22222222
J64: {=IF($G64="","", _xlfn.LET( _xlpm.topic,$G64, _xlpm.src,_xlfn._xlws.FILTER('Test Cases'!A55:F1059,ISNUMBER(SEARCH("-",'Test Cases'!A55:A1059))), _xlpm.topics,_xlfn.MAP(INDEX(_xlpm.src,,1),_xlfn.LAMBDA(_xlpm.x, _xlfn.LET( _xlpm.t,TRIM(_xlfn.TEXTAFTER(_xlpm.x,"-")), IFERROR(_xlfn.TEXTBEFORE(_xlpm.t," ",2),_xlpm.t) ) )), _xlpm.answers,INDEX(_xlpm.src,,4), _xlpm.denom,SUM(--(_xlpm.topics=_xlpm.topic)), IFERROR(SUM((_xlpm.topics=_xlpm.topic)*(_xlpm.answers="No"))/_xlpm.denom,"") ) )} | K64: {=IF($G64="","", _xlfn.LET( _xlpm.topic,$G64, _xlpm.src,_xlfn._xlws.FILTER('Test Cases'!A55:F1059,ISNUMBER(SEARCH("-",'Test Cases'!A55:A1059))), _xlpm.topics,_xlfn.MAP(INDEX(_xlpm.src,,1),_xlfn.LAMBDA(_xlpm.x, _xlfn.LET( _xlpm.t,TRIM(_xlfn.TEXTAFTER(_xlpm.x,"-")), IFERROR(_xlfn.TEXTBEFORE(_xlpm.t," ",2),_xlpm.t) ) )), _xlpm.answers,INDEX(_xlpm.src,,4), _xlpm.denom,SUM(--(_xlpm.topics=_xlpm.topic)), IFERROR(SUM((_xlpm.topics=_xlpm.topic)*(_xlpm.answers=""))/_xlpm.denom,"") ) )}
J65: {=IF($G65="","", _xlfn.LET( _xlpm.topic,$G65, _xlpm.src,_xlfn._xlws.FILTER('Test Cases'!A56:F1060,ISNUMBER(SEARCH("-",'Test Cases'!A56:A1060))), _xlpm.topics,_xlfn.MAP(INDEX(_xlpm.src,,1),_xlfn.LAMBDA(_xlpm.x, _xlfn.LET( _xlpm.t,TRIM(_xlfn.TEXTAFTER(_xlpm.x,"-")), IFERROR(_xlfn.TEXTBEFORE(_xlpm.t," ",2),_xlpm.t) ) )), _xlpm.answers,INDEX(_xlpm.src,,4), _xlpm.denom,SUM(--(_xlpm.topics=_xlpm.topic)), IFERROR(SUM((_xlpm.topics=_xlpm.topic)*(_xlpm.answers="No"))/_xlpm.denom,"") ) )} | K65: {=IF($G65="","", _xlfn.LET( _xlpm.topic,$G65, _xlpm.src,_xlfn._xlws.FILTER('Test Cases'!A56:F1060,ISNUMBER(SEARCH("-",'Test Cases'!A56:A1060))), _xlpm.topics,_xlfn.MAP(INDEX(_xlpm.src,,1),_xlfn.LAMBDA(_xlpm.x, _xlfn.LET( _xlpm.t,TRIM(_xlfn.TEXTAFTER(_xlpm.x,"-")), IFERROR(_xlfn.TEXTBEFORE(_xlpm.t," ",2),_xlpm.t) ) )), _xlpm.answers,INDEX(_xlpm.src,,4), _xlpm.denom,SUM(--(_xlpm.topics=_xlpm.topic)), IFERROR(SUM((_xlpm.topics=_xlpm.topic)*(_xlpm.answers=""))/_xlpm.denom,"") ) )}
J66: {=IF($G66="","", _xlfn.LET( _xlpm.topic,$G66, _xlpm.src,_xlfn._xlws.FILTER('Test Cases'!A57:F1061,ISNUMBER(SEARCH("-",'Test Cases'!A57:A1061))), _xlpm.topics,_xlfn.MAP(INDEX(_xlpm.src,,1),_xlfn.LAMBDA(_xlpm.x, _xlfn.LET( _xlpm.t,TRIM(_xlfn.TEXTAFTER(_xlpm.x,"-")), IFERROR(_xlfn.TEXTBEFORE(_xlpm.t," ",2),_xlpm.t) ) )), _xlpm.answers,INDEX(_xlpm.src,,4), _xlpm.denom,SUM(--(_xlpm.topics=_xlpm.topic)), IFERROR(SUM((_xlpm.topics=_xlpm.topic)*(_xlpm.answers="No"))/_xlpm.denom,"") ) )} | K66: {=IF($G66="","", _xlfn.LET( _xlpm.topic,$G66, _xlpm.src,_xlfn._xlws.FILTER('Test Cases'!A57:F1061,ISNUMBER(SEARCH("-",'Test Cases'!A57:A1061))), _xlpm.topics,_xlfn.MAP(INDEX(_xlpm.src,,1),_xlfn.LAMBDA(_xlpm.x, _xlfn.LET( _xlpm.t,TRIM(_xlfn.TEXTAFTER(_xlpm.x,"-")), IFERROR(_xlfn.TEXTBEFORE(_xlpm.t," ",2),_xlpm.t) ) )), _xlpm.answers,INDEX(_xlpm.src,,4), _xlpm.denom,SUM(--(_xlpm.topics=_xlpm.topic)), IFERROR(SUM((_xlpm.topics=_xlpm.topic)*(_xlpm.answers=""))/_xlpm.denom,"") ) )}
J67: {=IF($G67="","", _xlfn.LET( _xlpm.topic,$G67, _xlpm.src,_xlfn._xlws.FILTER('Test Cases'!A58:F1062,ISNUMBER(SEARCH("-",'Test Cases'!A58:A1062))), _xlpm.topics,_xlfn.MAP(INDEX(_xlpm.src,,1),_xlfn.LAMBDA(_xlpm.x, _xlfn.LET( _xlpm.t,TRIM(_xlfn.TEXTAFTER(_xlpm.x,"-")), IFERROR(_xlfn.TEXTBEFORE(_xlpm.t," ",2),_xlpm.t) ) )), _xlpm.answers,INDEX(_xlpm.src,,4), _xlpm.denom,SUM(--(_xlpm.topics=_xlpm.topic)), IFERROR(SUM((_xlpm.topics=_xlpm.topic)*(_xlpm.answers="No"))/_xlpm.denom,"") ) )} | K67: {=IF($G67="","", _xlfn.LET( _xlpm.topic,$G67, _xlpm.src,_xlfn._xlws.FILTER('Test Cases'!A58:F1062,ISNUMBER(SEARCH("-",'Test Cases'!A58:A1062))), _xlpm.topics,_xlfn.MAP(INDEX(_xlpm.src,,1),_xlfn.LAMBDA(_xlpm.x, _xlfn.LET( _xlpm.t,TRIM(_xlfn.TEXTAFTER(_xlpm.x,"-")), IFERROR(_xlfn.TEXTBEFORE(_xlpm.t," ",2),_xlpm.t) ) )), _xlpm.answers,INDEX(_xlpm.src,,4), _xlpm.denom,SUM(--(_xlpm.topics=_xlpm.topic)), IFERROR(SUM((_xlpm.topics=_xlpm.topic)*(_xlpm.answers=""))/_xlpm.denom,"") ) )}
J68: {=IF($G68="","", _xlfn.LET( _xlpm.topic,$G68, _xlpm.src,_xlfn._xlws.FILTER('Test Cases'!A59:F1063,ISNUMBER(SEARCH("-",'Test Cases'!A59:A1063))), _xlpm.topics,_xlfn.MAP(INDEX(_xlpm.src,,1),_xlfn.LAMBDA(_xlpm.x, _xlfn.LET( _xlpm.t,TRIM(_xlfn.TEXTAFTER(_xlpm.x,"-")), IFERROR(_xlfn.TEXTBEFORE(_xlpm.t," ",2),_xlpm.t) ) )), _xlpm.answers,INDEX(_xlpm.src,,4), _xlpm.denom,SUM(--(_xlpm.topics=_xlpm.topic)), IFERROR(SUM((_xlpm.topics=_xlpm.topic)*(_xlpm.answers="No"))/_xlpm.denom,"") ) )} | K68: {=IF($G68="","", _xlfn.LET( _xlpm.topic,$G68, _xlpm.src,_xlfn._xlws.FILTER('Test Cases'!A59:F1063,ISNUMBER(SEARCH("-",'Test Cases'!A59:A1063))), _xlpm.topics,_xlfn.MAP(INDEX(_xlpm.src,,1),_xlfn.LAMBDA(_xlpm.x, _xlfn.LET( _xlpm.t,TRIM(_xlfn.TEXTAFTER(_xlpm.x,"-")), IFERROR(_xlfn.TEXTBEFORE(_xlpm.t," ",2),_xlpm.t) ) )), _xlpm.answers,INDEX(_xlpm.src,,4), _xlpm.denom,SUM(--(_xlpm.topics=_xlpm.topic)), IFERROR(SUM((_xlpm.topics=_xlpm.topic)*(_xlpm.answers=""))/_xlpm.denom,"") ) )}
J69: {=IF($G69="","", _xlfn.LET( _xlpm.topic,$G69, _xlpm.src,_xlfn._xlws.FILTER('Test Cases'!A60:F1064,ISNUMBER(SEARCH("-",'Test Cases'!A60:A1064))), _xlpm.topics,_xlfn.MAP(INDEX(_xlpm.src,,1),_xlfn.LAMBDA(_xlpm.x, _xlfn.LET( _xlpm.t,TRIM(_xlfn.TEXTAFTER(_xlpm.x,"-")), IFERROR(_xlfn.TEXTBEFORE(_xlpm.t," ",2),_xlpm.t) ) )), _xlpm.answers,INDEX(_xlpm.src,,4), _xlpm.denom,SUM(--(_xlpm.topics=_xlpm.topic)), IFERROR(SUM((_xlpm.topics=_xlpm.topic)*(_xlpm.answers="No"))/_xlpm.denom,"") ) )} | K69: {=IF($G69="","", _xlfn.LET( _xlpm.topic,$G69, _xlpm.src,_xlfn._xlws.FILTER('Test Cases'!A60:F1064,ISNUMBER(SEARCH("-",'Test Cases'!A60:A1064))), _xlpm.topics,_xlfn.MAP(INDEX(_xlpm.src,,1),_xlfn.LAMBDA(_xlpm.x, _xlfn.LET( _xlpm.t,TRIM(_xlfn.TEXTAFTER(_xlpm.x,"-")), IFERROR(_xlfn.TEXTBEFORE(_xlpm.t," ",2),_xlpm.t) ) )), _xlpm.answers,INDEX(_xlpm.src,,4), _xlpm.denom,SUM(--(_xlpm.topics=_xlpm.topic)), IFERROR(SUM((_xlpm.topics=_xlpm.topic)*(_xlpm.answers=""))/_xlpm.denom,"") ) )}
J70: {=IF($G70="","", _xlfn.LET( _xlpm.topic,$G70, _xlpm.src,_xlfn._xlws.FILTER('Test Cases'!A61:F1065,ISNUMBER(SEARCH("-",'Test Cases'!A61:A1065))), _xlpm.topics,_xlfn.MAP(INDEX(_xlpm.src,,1),_xlfn.LAMBDA(_xlpm.x, _xlfn.LET( _xlpm.t,TRIM(_xlfn.TEXTAFTER(_xlpm.x,"-")), IFERROR(_xlfn.TEXTBEFORE(_xlpm.t," ",2),_xlpm.t) ) )), _xlpm.answers,INDEX(_xlpm.src,,4), _xlpm.denom,SUM(--(_xlpm.topics=_xlpm.topic)), IFERROR(SUM((_xlpm.topics=_xlpm.topic)*(_xlpm.answers="No"))/_xlpm.denom,"") ) )} | K70: {=IF($G70="","", _xlfn.LET( _xlpm.topic,$G70, _xlpm.src,_xlfn._xlws.FILTER('Test Cases'!A61:F1065,ISNUMBER(SEARCH("-",'Test Cases'!A61:A1065))), _xlpm.topics,_xlfn.MAP(INDEX(_xlpm.src,,1),_xlfn.LAMBDA(_xlpm.x, _xlfn.LET( _xlpm.t,TRIM(_xlfn.TEXTAFTER(_xlpm.x,"-")), IFERROR(_xlfn.TEXTBEFORE(_xlpm.t," ",2),_xlpm.t) ) )), _xlpm.answers,INDEX(_xlpm.src,,4), _xlpm.denom,SUM(--(_xlpm.topics=_xlpm.topic)), IFERROR(SUM((_xlpm.topics=_xlpm.topic)*(_xlpm.answers=""))/_xlpm.denom,"") ) )}
J71: {=IF($G71="","", _xlfn.LET( _xlpm.topic,$G71, _xlpm.src,_xlfn._xlws.FILTER('Test Cases'!A62:F1066,ISNUMBER(SEARCH("-",'Test Cases'!A62:A1066))), _xlpm.topics,_xlfn.MAP(INDEX(_xlpm.src,,1),_xlfn.LAMBDA(_xlpm.x, _xlfn.LET( _xlpm.t,TRIM(_xlfn.TEXTAFTER(_xlpm.x,"-")), IFERROR(_xlfn.TEXTBEFORE(_xlpm.t," ",2),_xlpm.t) ) )), _xlpm.answers,INDEX(_xlpm.src,,4), _xlpm.denom,SUM(--(_xlpm.topics=_xlpm.topic)), IFERROR(SUM((_xlpm.topics=_xlpm.topic)*(_xlpm.answers="No"))/_xlpm.denom,"") ) )} | K71: {=IF($G71="","", _xlfn.LET( _xlpm.topic,$G71, _xlpm.src,_xlfn._xlws.FILTER('Test Cases'!A62:F1066,ISNUMBER(SEARCH("-",'Test Cases'!A62:A1066))), _xlpm.topics,_xlfn.MAP(INDEX(_xlpm.src,,1),_xlfn.LAMBDA(_xlpm.x, _xlfn.LET( _xlpm.t,TRIM(_xlfn.TEXTAFTER(_xlpm.x,"-")), IFERROR(_xlfn.TEXTBEFORE(_xlpm.t," ",2),_xlpm.t) ) )), _xlpm.answers,INDEX(_xlpm.src,,4), _xlpm.denom,SUM(--(_xlpm.topics=_xlpm.topic)), IFERROR(SUM((_xlpm.topics=_xlpm.topic)*(_xlpm.answers=""))/_xlpm.denom,"") ) )}
J72: {=IF($G72="","", _xlfn.LET( _xlpm.topic,$G72, _xlpm.src,_xlfn._xlws.FILTER('Test Cases'!A63:F1067,ISNUMBER(SEARCH("-",'Test Cases'!A63:A1067))), _xlpm.topics,_xlfn.MAP(INDEX(_xlpm.src,,1),_xlfn.LAMBDA(_xlpm.x, _xlfn.LET( _xlpm.t,TRIM(_xlfn.TEXTAFTER(_xlpm.x,"-")), IFERROR(_xlfn.TEXTBEFORE(_xlpm.t," ",2),_xlpm.t) ) )), _xlpm.answers,INDEX(_xlpm.src,,4), _xlpm.denom,SUM(--(_xlpm.topics=_xlpm.topic)), IFERROR(SUM((_xlpm.topics=_xlpm.topic)*(_xlpm.answers="No"))/_xlpm.denom,"") ) )} | K72: {=IF($G72="","", _xlfn.LET( _xlpm.topic,$G72, _xlpm.src,_xlfn._xlws.FILTER('Test Cases'!A63:F1067,ISNUMBER(SEARCH("-",'Test Cases'!A63:A1067))), _xlpm.topics,_xlfn.MAP(INDEX(_xlpm.src,,1),_xlfn.LAMBDA(_xlpm.x, _xlfn.LET( _xlpm.t,TRIM(_xlfn.TEXTAFTER(_xlpm.x,"-")), IFERROR(_xlfn.TEXTBEFORE(_xlpm.t," ",2),_xlpm.t) ) )), _xlpm.answers,INDEX(_xlpm.src,,4), _xlpm.denom,SUM(--(_xlpm.topics=_xlpm.topic)), IFERROR(SUM((_xlpm.topics=_xlpm.topic)*(_xlpm.answers=""))/_xlpm.denom,"") ) )}
J73: {=IF($G73="","", _xlfn.LET( _xlpm.topic,$G73, _xlpm.src,_xlfn._xlws.FILTER('Test Cases'!A64:F1068,ISNUMBER(SEARCH("-",'Test Cases'!A64:A1068))), _xlpm.topics,_xlfn.MAP(INDEX(_xlpm.src,,1),_xlfn.LAMBDA(_xlpm.x, _xlfn.LET( _xlpm.t,TRIM(_xlfn.TEXTAFTER(_xlpm.x,"-")), IFERROR(_xlfn.TEXTBEFORE(_xlpm.t," ",2),_xlpm.t) ) )), _xlpm.answers,INDEX(_xlpm.src,,4), _xlpm.denom,SUM(--(_xlpm.topics=_xlpm.topic)), IFERROR(SUM((_xlpm.topics=_xlpm.topic)*(_xlpm.answers="No"))/_xlpm.denom,"") ) )} | K73: {=IF($G73="","", _xlfn.LET( _xlpm.topic,$G73, _xlpm.src,_xlfn._xlws.FILTER('Test Cases'!A64:F1068,ISNUMBER(SEARCH("-",'Test Cases'!A64:A1068))), _xlpm.topics,_xlfn.MAP(INDEX(_xlpm.src,,1),_xlfn.LAMBDA(_xlpm.x, _xlfn.LET( _xlpm.t,TRIM(_xlfn.TEXTAFTER(_xlpm.x,"-")), IFERROR(_xlfn.TEXTBEFORE(_xlpm.t," ",2),_xlpm.t) ) )), _xlpm.answers,INDEX(_xlpm.src,,4), _xlpm.denom,SUM(--(_xlpm.topics=_xlpm.topic)), IFERROR(SUM((_xlpm.topics=_xlpm.topic)*(_xlpm.answers=""))/_xlpm.denom,"") ) )}
J74: {=IF($G74="","", _xlfn.LET( _xlpm.topic,$G74, _xlpm.src,_xlfn._xlws.FILTER('Test Cases'!A65:F1069,ISNUMBER(SEARCH("-",'Test Cases'!A65:A1069))), _xlpm.topics,_xlfn.MAP(INDEX(_xlpm.src,,1),_xlfn.LAMBDA(_xlpm.x, _xlfn.LET( _xlpm.t,TRIM(_xlfn.TEXTAFTER(_xlpm.x,"-")), IFERROR(_xlfn.TEXTBEFORE(_xlpm.t," ",2),_xlpm.t) ) )), _xlpm.answers,INDEX(_xlpm.src,,4), _xlpm.denom,SUM(--(_xlpm.topics=_xlpm.topic)), IFERROR(SUM((_xlpm.topics=_xlpm.topic)*(_xlpm.answers="No"))/_xlpm.denom,"") ) )} | K74: {=IF($G74="","", _xlfn.LET( _xlpm.topic,$G74, _xlpm.src,_xlfn._xlws.FILTER('Test Cases'!A65:F1069,ISNUMBER(SEARCH("-",'Test Cases'!A65:A1069))), _xlpm.topics,_xlfn.MAP(INDEX(_xlpm.src,,1),_xlfn.LAMBDA(_xlpm.x, _xlfn.LET( _xlpm.t,TRIM(_xlfn.TEXTAFTER(_xlpm.x,"-")), IFERROR(_xlfn.TEXTBEFORE(_xlpm.t," ",2),_xlpm.t) ) )), _xlpm.answers,INDEX(_xlpm.src,,4), _xlpm.denom,SUM(--(_xlpm.topics=_xlpm.topic)), IFERROR(SUM((_xlpm.topics=_xlpm.topic)*(_xlpm.answers=""))/_xlpm.denom,"") ) )}
J75: {=IF($G75="","", _xlfn.LET( _xlpm.topic,$G75, _xlpm.src,_xlfn._xlws.FILTER('Test Cases'!A66:F1070,ISNUMBER(SEARCH("-",'Test Cases'!A66:A1070))), _xlpm.topics,_xlfn.MAP(INDEX(_xlpm.src,,1),_xlfn.LAMBDA(_xlpm.x, _xlfn.LET( _xlpm.t,TRIM(_xlfn.TEXTAFTER(_xlpm.x,"-")), IFERROR(_xlfn.TEXTBEFORE(_xlpm.t," ",2),_xlpm.t) ) )), _xlpm.answers,INDEX(_xlpm.src,,4), _xlpm.denom,SUM(--(_xlpm.topics=_xlpm.topic)), IFERROR(SUM((_xlpm.topics=_xlpm.topic)*(_xlpm.answers="No"))/_xlpm.denom,"") ) )} | K75: {=IF($G75="","", _xlfn.LET( _xlpm.topic,$G75, _xlpm.src,_xlfn._xlws.FILTER('Test Cases'!A66:F1070,ISNUMBER(SEARCH("-",'Test Cases'!A66:A1070))), _xlpm.topics,_xlfn.MAP(INDEX(_xlpm.src,,1),_xlfn.LAMBDA(_xlpm.x, _xlfn.LET( _xlpm.t,TRIM(_xlfn.TEXTAFTER(_xlpm.x,"-")), IFERROR(_xlfn.TEXTBEFORE(_xlpm.t," ",2),_xlpm.t) ) )), _xlpm.answers,INDEX(_xlpm.src,,4), _xlpm.denom,SUM(--(_xlpm.topics=_xlpm.topic)), IFERROR(SUM((_xlpm.topics=_xlpm.topic)*(_xlpm.answers=""))/_xlpm.denom,"") ) )}
... J104: {=IF($G104="","", _xlfn.LET( _xlpm.topic,$G104, _xlpm.src,_xlfn._xlws.FILTER('Test Cases'!A95:F1099,ISNUMBER(SEARCH("-",'Test Cases'!A95:A1099))), _xlpm.topics,_xlfn.MAP(INDEX(_xlpm.src,,1),_xlfn.LAMBDA(_xlpm.x, _xlfn.LET( _xlpm.t,TRIM(_xlfn.TEXTAFTER(_xlpm.x,"-")), IFERROR(_xlfn.TEXTBEFORE(_xlpm.t," ",2),_xlpm.t) ) )), _xlpm.answers,INDEX(_xlpm.src,,4), _xlpm.denom,SUM(--(_xlpm.topics=_xlpm.topic)), IFERROR(SUM((_xlpm.topics=_xlpm.topic)*(_xlpm.answers="No"))/_xlpm.denom,"") ) )} | K104: {=IF($G104="","", _xlfn.LET( _xlpm.topic,$G104, _xlpm.src,_xlfn._xlws.FILTER('Test Cases'!A95:F1099,ISNUMBER(SEARCH("-",'Test Cases'!A95:A1099))), _xlpm.topics,_xlfn.MAP(INDEX(_xlpm.src,,1),_xlfn.LAMBDA(_xlpm.x, _xlfn.LET( _xlpm.t,TRIM(_xlfn.TEXTAFTER(_xlpm.x,"-")), IFERROR(_xlfn.TEXTBEFORE(_xlpm.t," ",2),_xlpm.t) ) )), _xlpm.answers,INDEX(_xlpm.src,,4), _xlpm.denom,SUM(--(_xlpm.topics=_xlpm.topic)), IFERROR(SUM((_xlpm.topics=_xlpm.topic)*(_xlpm.answers=""))/_xlpm.denom,"") ) )}

Sheet Test Cases
A1: Scenario | B1: Topic Area | C1: Test Question | D1: Prod Answer | E1: General Notes | F1: FoundAnswer | G1: Claude Found? | H1: AnswerQuality | I1: CorrectSources | J1: Test Date | K1: Perfomance | L1: Clarification | M1: Expected Behavior | N1: Date Created | O1: Column1
A2: Happy path - DA project planning [DA] | B2: =_xlfn.TEXTBEFORE(_xlfn.TEXTAFTER(A2,"[",-1),"]") -> DA | C2: What is required in a DA concept note? | D2: Answer: Intent Identified: You are seeking a comprehensive summary of the required sections and planning/design requirements for a Development Account (DA) concept note, referencing the latest (19th tranche) guidelines, templates, and review checklists, with a focus on project planning, objectives, budget, results framework, quality assurance, internal review, submission, and implementing entity. Required Sections for a DA Concept Note (19th Tranche): Background: Describe the issue, context, human rights, gender, disability inclusion, demand from Member States, tentative target countries, and link to implementing entity. Fascicle Note: Title, implementing entity and partners, SDG targets, objective, project plan for 2027–2030, budget summary, and additional required tables. Outcomes and Outputs (Results Framework): At least two outcomes and linked outputs with strong logical linkages. UN System Coordination: Plans for engaging RCOs and UN Country Teams, and key partnerships. Budget Narrative: Detailed breakdown by budget class using required tables and formats. Planning/Design Requirements: Use the latest template (Annex 1). Quality Assurance and Internal Review: Internal quality review using the provided checklist. Submission Requirements: Submit twice the number of projects as funded previously, prioritize special needs countries, and meet criteria for joint projects. Implementing Entity: Must be one of the 10 DA entities, clearly stating lead, joint, and collaborating entities. Key Quality and Planning Considerations: Link to tranche theme and capacity development. Address implementing unit capacity. Exclude evaluation costs at concept note stage. Provide all data in requested format. Reference to Latest Guidelines, Templates, and Checklists: Guidelines: 19th tranche Concept Note Guidelines. Template: 19th tranche Concept Note Template (Annex 1). Review Checklist: 19th tranche Concept Note Review Checklist for DA Focal Points. Sources: T19 Concept Note Guidelines.docx T19 Concept Note Template.docx T19 Concept Note Review Checklist for DA Focal Points.docx Confidence: Very High | F2: Yes | I2: Yes | J2: 46184 | K2: less than 15secs | M2: Intent Classifier sets knowledge_domain=da, funding_stream=DA, topic_area=project_planning_design, requires_clarification=No. Intent Clarifier bypasses. Intent Router routes to Formulate Response DA.
A3: Happy path - DA project document [DA] | B3: =_xlfn.TEXTBEFORE(_xlfn.TEXTAFTER(A3,"[",-1),"]") -> DA | C3: For DA, how do I prepare a project document? | D3: Answer: You are seeking a comprehensive, step-by-step overview of the process and requirements for preparing a Development Account (DA) project document for the latest tranche, including all key elements, required tools, and quality assurance steps. Use the Most Recent Guidance and Templates Always use the latest tranche’s guidelines and templates (currently the 19th tranche, T19) for project documents, unless an earlier tranche is specifically requested. The main sources are the T19 Project Document Guidelines, the T19 Project Document Template, the T19 Project Document Annex (Excel), and the T19 Project Document Review Checklist for DA Focal Points. The guidelines provide detailed instructions for each section; the template is for drafting; the Excel annex is for workplans and budget tables; the checklist is for internal review before submission. Project Planning and Preparation Steps Expand the concept note into a full project document, using feedback from the concept note review. Drafting typically occurs from May to September of the relevant year (e.g., 2026 for T19). Confirm target countries and consult the Resident Coordinator Office (RCO) in each target country during drafting. For joint projects, ensure all jointly implementing entities agree on strategy, roles, and budget distribution before submission. Structure and Key Elements of the Project Document Executive Summary: Project code/title, implementing entity, jointly implementing/collaborating entities, implementing partners, end date, budget, use of IPMR, target countries, SDG relevance, and a brief description (max 300 words). Demand, Context, and Analysis: Selection and rationale for target countries, context and situation analysis (including gender/disability/vulnerable groups), country-level analysis, and (optionally) stakeholder analysis. Project Strategy: Envisaged change in the countries (concrete change sought). Theory of change narrative and main assumptions. Results framework (objective, outcomes, indicators, baselines, means of verification, outputs). Results-based workplan (in Excel annex). Risks and mitigating actions. Post-project sustainability and scaling-up. Lessons learned from past projects. Gender Equality and Disability Inclusion: Assign and justify gender and disability markers, ensuring alignment with the results framework. Monitoring, Reporting, and Evaluation: Explain monitoring arrangements, reporting intervals, and evaluation plans. For joint projects over $1 million, include a detailed evaluation plan and annual monitoring calls. Mandates, Partnerships, and Coordination Agreements: Describe mandates, roles, and responsibilities of all entities. For joint projects, confirm shared outcomes and joint outputs, and establish a Project Steering Committee. List implementing partners and describe their roles and budget share. Document RCO engagement for each target country. Budget: Complete all required budget tables in the Excel annex, following guidance in section 7 of the guidelines. Consult finance colleagues for joint projects. Ensure compliance with rules on staff capacity, travel, and use of consultants/partners. Quality Assurance and Internal Review Use the T19 Project Document Review Checklist for DA Focal Points to ensure all requirements are met before submission. The checklist covers all sections, including budget accuracy, alignment of entities, clarity of objectives, results framework, gender/disability markers, monitoring/evaluation, and RCO engagement. The DA Focal Point must complete the checklist and confirm internal quality assurance before submission. Submission Process Submit the draft project document to the DA Programme Management Team (DA-PMT) by the specified deadlines (e.g., 30 June for at least one document per entity, all by 15 September). Submissions are accepted on a rolling basis as documents are ready. Only submit after thorough internal review and quality control. Implementing Entity Requirements The lead implementing entity is responsible for overall coordination, quality assurance, and reporting. For joint projects, all jointly implementing entities must be involved in design, implementation, monitoring, and evaluation. The Project Steering Committee (for joint projects) oversees coordination and performance. Summary Table of Required Tools and Elements | Element | Source/Tool | |------------------------------- |----------------------------------------------| | Guidelines | T19 Project Document Guidelines | | Drafting Template | T19 Project Document Template | | Budget/Workplan | T19 Project Document Annex (Excel) | | Quality Assurance | T19 Project Document Review Checklist | | Internal Review | DA Focal Point review and checklist | | Submission | To DA-PMT after internal QA | | Implementing Entity | Lead and (if joint) jointly implementing | Sources: T19 Project Document Guidelines.docx T19 Project Document Template.docx T19 Project Document Annex.xlsx T19 Project Document Review Checklist for DA Focal Points.docx readme.docx Confidence: Very High | F3: Yes | I3: Yes | J3: 46184 | K3: less than 15secs | M3: Routes directly to Formulate Response DA with topic_area=project_planning_design.
A4: Happy path - DA monitoring and reporting [DA] | B4: =_xlfn.TEXTBEFORE(_xlfn.TEXTAFTER(A4,"[",-1),"]") -> DA | C4: What are the DA requirements for project monitoring and reporting? | D4: Answer: I was not able to find information in my knowledge sources that could answer this question. Sources: No sources found. Confidence: Low | F4: No | J4: 46184 | K4: less than 15secs | M4: Routes directly to Formulate Response DA with topic_area=monitoring_reporting.
A5: Happy path - DA budget eligibility [DA] | B5: =_xlfn.TEXTBEFORE(_xlfn.TEXTAFTER(A5,"[",-1),"]") -> DA | C5: Under the Development Account, are travel costs eligible? | D5: Answer: Yes, under the Development Account, travel costs are considered eligible expenses. Specifically, the budget class "Travel of Staff (115)" is used exclusively for the travel of UN system-wide staff for all types of travel, including participation in expert groups, workshops, and providing advisory services. However, staff travel costs should not be included under "Grants and Contributions – Workshops/Study Tours (145)", which is reserved for the travel/DSA of participants attending seminars, workshops, study tours, and expert group meetings. The number of staff traveling per activity should be limited, especially if there are consultants traveling for the same activity. For joint projects, careful consideration should be given to the necessity of travel, and hybrid or virtual options should be utilized where possible to manage costs effectively. Sources: T16 Project Document Guidelines v6 final.pdf T19 Concept Note Guidelines.docx T18 Project Document Guidelines.docx T19 Project Document Guidelines.docx Confidence: Very High | F5: Yes | I5: Yes | J5: 46184 | M5: Routes directly to Formulate Response DA with topic_area=budget_finance or eligibility_budget if available.
A6: Happy path - DA Section 35 signal [DA] | B6: =_xlfn.TEXTBEFORE(_xlfn.TEXTAFTER(A6,"[",-1),"]") -> DA | C6: What does Section 35 say about project design? | D6: Answer: I was not able to find information in my knowledge sources that could answer this question. Sources: No sources found. Confidence: Low | F6: No | J6: 46184 | M6: Recognizes Section 35 as DA signal and routes to Formulate Response DA.
A7: Happy path - DA evaluation design [DA] | B7: =_xlfn.TEXTBEFORE(_xlfn.TEXTAFTER(A7,"[",-1),"]") -> DA | C7: How do I design a DA terminal evaluation? | D7: Answer: 1. Official Guidance and Requirements Terminal evaluations are mandatory for all DA projects with a budget of USD 1 million or more and are strongly encouraged for others selected at midterm. The process and structure are governed by the DA Project Evaluation Guidelines, the Administrative Instructions on Evaluation in the UN Secretariat (ST/AI/2021/3), and tranche-specific guidance notes. For joint projects, refer to the DA guidance note on terminal evaluation of joint projects (latest version: June 2023, V.1). Evaluation Design Steps Preparatory Phase Develop a detailed tentative evaluation plan as part of the project document, including: Timeline (evaluation report due within 9 months of project completion for projects ≥ USD 1 million; 6 months for others) Target users and intended use of results Management and support arrangements Preliminary methodology Tentative budget (up to 4% of final project budget) Follow-up plan Development of Terms of Reference (TOR) Start at least 6 months before project completion. TOR should include: Purpose and objectives of the evaluation Project context and description Evaluation scope, criteria, and tentative questions Methodology (see below) List of key stakeholders Organization, roles, responsibilities, workplan, and deliverables Dissemination strategy Evaluation budget and required evaluator qualifications Integration of human rights, gender equality, and, where possible, disability perspectives Required Methodology Use a mixed-methods approach, ensuring triangulation of data sources for confidence in findings. Typical methods include: Desk review of project documents and data Interviews (in-person or remote) Focus group discussions Online surveys Field visits (for beneficiary feedback not easily collected remotely) Observation of workshops/meetings Methodology should be tailored to the project’s scope, activities, geographic coverage, and available data and budget. For joint projects, ensure data collection covers all implementing entities, not just the lead. Evaluation Report Structure Use the DA project evaluation report template (or, if required, the entity’s own template with all DA-required elements included). Key sections: Executive summary Description of the project (context, objectives, strategies, partners, resources, SDG links, innovative elements) Evaluation objectives, scope, and questions Methodology (including rationale, data sources, sampling, ethical standards, integration of gender/human rights/disability) Findings (evidence-based, linked to criteria/questions, gender-disaggregated where relevant) Conclusions Recommendations (practical, feasible, directed to intended users) Lessons learned and good practices (for broader dissemination) Annexes (TOR, results framework, evaluation matrix, data collection tools, list of interviews/documents) Management and Follow-up Each implementing entity is responsible for developing a management response to recommendations within 3 months of report finalization. Management responses and evaluation reports are published on the DA website and entities’ own sites. Entities must track implementation of accepted recommendations. Reference to Official Guidance Use the latest DA Project Evaluation Guidelines, tranche-specific guidance notes, and the DA guidance note on terminal evaluation of joint projects (June 2023, V.1) for detailed instructions and templates. Sources: DA guidance note on terminal evaluation of joint projects v1.pdf Guide to the Development Account 2025.pdf T15 DA project evaluation report template (annotated).docx T15 DA guidance note on project evaluations - re re final 2.3.2026.docx Confidence: Very High | F7: Yes | I7: Yes | J7: 46184 | M7: Routes directly to Formulate Response DA with topic_area=evaluation_design. This is guidance on designing an evaluation, not actual evaluation evidence.
A8: Happy path - DA evaluation template [DA] | B8: =_xlfn.TEXTBEFORE(_xlfn.TEXTAFTER(A8,"[",-1),"]") -> DA | C8: What is the DA evaluation report template? | D8: Answer: 1. Official Guidance and Requirements Terminal evaluations are mandatory for all DA projects with a budget of USD 1 million or more and are strongly encouraged for others selected at midterm. The process and structure are governed by the DA Project Evaluation Guidelines, the Administrative Instructions on Evaluation in the UN Secretariat (ST/AI/2021/3), and tranche-specific guidance notes. For joint projects, refer to the DA guidance note on terminal evaluation of joint projects (latest version: June 2023, V.1). Evaluation Design Steps Preparatory Phase Develop a detailed tentative evaluation plan as part of the project document, including: Timeline (evaluation report due within 9 months of project completion for projects ≥ USD 1 million; 6 months for others) Target users and intended use of results Management and support arrangements Preliminary methodology Tentative budget (up to 4% of final project budget) Follow-up plan Development of Terms of Reference (TOR) Start at least 6 months before project completion. TOR should include: Purpose and objectives of the evaluation Project context and description Evaluation scope, criteria, and tentative questions Methodology (see below) List of key stakeholders Organization, roles, responsibilities, workplan, and deliverables Dissemination strategy Evaluation budget and required evaluator qualifications Integration of human rights, gender equality, and, where possible, disability perspectives Required Methodology Use a mixed-methods approach, ensuring triangulation of data sources for confidence in findings. Typical methods include: Desk review of project documents and data Interviews (in-person or remote) Focus group discussions Online surveys Field visits (for beneficiary feedback not easily collected remotely) Observation of workshops/meetings Methodology should be tailored to the project’s scope, activities, geographic coverage, and available data and budget. For joint projects, ensure data collection covers all implementing entities, not just the lead. Evaluation Report Structure Use the DA project evaluation report template (or, if required, the entity’s own template with all DA-required elements included). Key sections: Executive summary Description of the project (context, objectives, strategies, partners, resources, SDG links, innovative elements) Evaluation objectives, scope, and questions Methodology (including rationale, data sources, sampling, ethical standards, integration of gender/human rights/disability) Findings (evidence-based, linked to criteria/questions, gender-disaggregated where relevant) Conclusions Recommendations (practical, feasible, directed to intended users) Lessons learned and good practices (for broader dissemination) Annexes (TOR, results framework, evaluation matrix, data collection tools, list of interviews/documents) Management and Follow-up Each implementing entity is responsible for developing a management response to recommendations within 3 months of report finalization. Management responses and evaluation reports are published on the DA website and entities’ own sites. Entities must track implementation of accepted recommendations. Reference to Official Guidance Use the latest DA Project Evaluation Guidelines, tranche-specific guidance notes, and the DA guidance note on terminal evaluation of joint projects (June 2023, V.1) for detailed instructions and templates. Sources: DA guidance note on terminal evaluation of joint projects v1.pdf Guide to the Development Account 2025.pdf T15 DA project evaluation report template (annotated).docx T15 DA guidance note on project evaluations - re re final 2.3.2026.docx Confidence: Very High | F8: Yes | I8: Yes | J8: 46184 | M8: Routes to Formulate Response DA with topic_area=evaluation_design or templates.
A9: Happy path - DA general start [DA] | B9: =_xlfn.TEXTBEFORE(_xlfn.TEXTAFTER(A9,"[",-1),"]") -> DA | C9: How do I start a new DA project? | D9: Answer: To initiate a new Development Account (DA) project, follow these steps: Understand the Planning Cycle: The DA project cycle begins about 1.5 years before the four-year implementation period. Each tranche is guided by a theme selected by the DA Steering Committee and approved by the Programme Manager. Draft a Concept Note: This is the first required document. It should align with the tranche theme, demonstrate demand from target countries, and outline objectives, expected results, and partnerships. Use the latest concept note guidelines and template from the DA website and SharePoint. Internal quality review by the DA Focal Point is mandatory before submission, typically due mid-November of the planning year. Shortlisting and Approval: Concept notes are reviewed by the DA-PMT, shortlisted, and approved by the DA Steering Committee and Programme Manager. Shortlisted projects are included in the UN Programme Budget for General Assembly approval. Draft a Project Document: After shortlisting, develop a detailed project document including theory of change, results framework, monitoring plan, and budget. Use tranche-specific guidelines and templates. Internal quality assurance and consultations with Resident Coordinator Offices are required. Deadline is typically mid-September of the planning year. Review and Finalization: The DA-PMT reviews and provides feedback. After revisions and final approval, the project is ready for fund allocation following General Assembly approval. Required Initial Documents: Concept Note (latest guidelines and template) Project Document (latest guidelines and template, after shortlisting) Always use the most recent tranche guidelines and coordinate with your DA Focal Point throughout the process. Sources: Guide to the Development Account 2025.pdf T19 Concept Note Guidelines.docx T19 Project Document Guidelines.docx Confidence: Very High | F9: Yes | I9: Yes | J9: 46184 | M9: Routes to Formulate Response DA. Topic may be general or project_planning_design.
A10: Happy path - DA latest tranche [DA] | B10: =_xlfn.TEXTBEFORE(_xlfn.TEXTAFTER(A10,"[",-1),"]") -> DA | C10: Which DA tranche guidance should I use for a new project? | D10: Answer: When starting a new Development Account (DA) project, you should always use the guidance for the most recent tranche available. The DA knowledge base specifies that the files and guidelines are organized by tranche number (e.g., T14, T15, T16, etc.), and you should reference the highest-numbered (most recent) tranche for the most up-to-date instructions. Only refer to earlier tranche guidance if you are specifically asked about a previous tranche. This ensures your project planning and documentation align with the latest requirements and processes set by the DA. Sources: readme.docx Confidence: Very High | F10: Yes | I10: No | J10: 46184 | M10: Routes to Formulate Response DA and should prefer the latest tranche guidance.
A11: Happy path - DA checklist [DA] | B11: =_xlfn.TEXTBEFORE(_xlfn.TEXTAFTER(A11,"[",-1),"]") -> DA | C11: Is there a DA checklist for reviewing concept notes? | D11: Answer: Yes, there is a checklist available for reviewing Development Account (DA) concept notes. The checklist is designed to assist DA Focal Points in reviewing each concept note before submission. It covers key sections such as: General: Ensuring the correct template is used and that the implementing section has sufficient resources. Background: Explanation of the issue, context, target countries, demand, and connection to the implementing entity’s work. Fascicle Note: Format, objective, project plan, and word count. Additional Data: Completion and formatting of required tables. Outcomes and Outputs: Sufficiency and clarity of outputs and their link to outcomes. UN System: Specific plans for engaging Resident Coordinator Offices (RCOs) and explanation of partnerships. Budget Summary: Correct format and accuracy of figures. The checklist is intended to ensure internal quality review and adherence to guidelines before submission to the DA Team. It is referenced in the most recent tranche guidance and is available as an annex to the concept note guidelines for the 19th tranche. Sources: T19 Concept Note Review Checklist for DA Focal Points.docx T19 Concept Note Guidelines.docx Confidence: Very High | F11: Yes | I11: Yes | M11: Routes to Formulate Response DA with topic_area=project_planning_design or templates.
A12: Happy path - project evaluation evidence [Evaluation] | B12: =_xlfn.TEXTBEFORE(_xlfn.TEXTAFTER(A12,"[",-1),"]") -> Evaluation | C12: What do project evaluations say about sustainability? | D12: Answer: I was not able to find information in my knowledge sources that could answer this question. Sources: No sources found. Confidence: Low | F12: No | M12: Routes directly to Programme Development with topic_area=projects_evaluations. This is actual evaluation evidence, not evaluation design guidance.
A13: Happy path - evaluation recommendations [Evaluation] | B13: =_xlfn.TEXTBEFORE(_xlfn.TEXTAFTER(A13,"[",-1),"]") -> Evaluation | C13: Summarize recommendations from project evaluations related to stakeholder engagement. | M13: Routes to Programme Development with topic_area=projects_evaluations.
A14: Happy path - lessons learned [Evaluation] | B14: =_xlfn.TEXTBEFORE(_xlfn.TEXTAFTER(A14,"[",-1),"]") -> Evaluation | C14: What lessons learned are available from past capacity development projects? | D14: I am sorry, I was not able to find a confident answer to your question in my knowledge sources. I am still under development and new knowledge is coming in every week. See ​Cidy Knowledge Status​ for more information. Sent at June 16 at 4:53 PM Bot said: I am sorry, I was not able to find a confident answer to your question in my knowledge sources. I am still under development and new knowledge is coming in every week. See ​Cidy Knowledge Status​ for more information. One or more links in the message. Bot said: Answer: I was not able to find information in my knowledge sources that could answer this question. Sources: No sources found. Confidence: Low | E14: Message about checking status shows up before the "answer"; Don't even see formulate response program dev in copilot studio but do in repo; no timer | F14: No | I14: n/a | J14: 46189 | M14: Routes to Programme Development with topic_area=projects_evaluations.
A15: Happy path - recurring evaluation findings [Evaluation] | B15: =_xlfn.TEXTBEFORE(_xlfn.TEXTAFTER(A15,"[",-1),"]") -> Evaluation | C15: What have evaluations said about DA projects? | D15: I am sorry, I was not able to find a confident answer to your question in my knowledge sources. I am still under development and new knowledge is coming in every week. See ​Cidy Knowledge Status​ for more information. Sent at June 16 at 5:11 PM Bot said: I am sorry, I was not able to find a confident answer to your question in my knowledge sources. I am still under development and new knowledge is coming in every week. See ​Cidy Knowledge Status​ for more information. One or more links in the message. Bot said: Answer: I was not able to find information in my knowledge sources that could answer this question. Sources: No sources found. Confidence: Low | E15: No timer, no formulate pd; naming convention is different, fixed timer | F15: No | I15: n/a | J15: 46189 | M15: Routes to Programme Development with topic_area=projects_evaluations, using DA as context if available. It should not route to DA evaluation design guidance.
A16: Happy path - evaluation weaknesses [Evaluation] | B16: =_xlfn.TEXTBEFORE(_xlfn.TEXTAFTER(A16,"[",-1),"]") -> Evaluation | C16: Are there recurring findings from past project evaluations? | D16: Same as above | F16: No | I16: n/a | J16: 46189 | M16: Routes to Programme Development with topic_area=projects_evaluations.
A17: Happy path - partnerships in evaluations [Evaluation] | B17: =_xlfn.TEXTBEFORE(_xlfn.TEXTAFTER(A17,"[",-1),"]") -> Evaluation | C17: What do evaluation reports say about project design weaknesses? | D17: Answer: Evaluation reports and lessons learned sections in project documentation highlight several common weaknesses in project design, based on findings from past evaluations: Insufficient problem analysis: Projects sometimes fail to clearly define the main problem and its underlying causes, leading to objectives that are too broad or not well-targeted. This can result in interventions that do not address the most critical issues or the needs of the most vulnerable groups. Lack of specificity in objectives and outcomes: Objectives and outcomes may be vaguely formulated, making it difficult to measure progress or success. Clear, specific, and measurable objectives are essential for effective monitoring and evaluation. Weak logical framework: The causal links between activities, outputs, outcomes, and objectives may not be well-articulated. This can lead to gaps in the results chain, where outputs do not sufficiently contribute to intended outcomes. Inadequate stakeholder analysis and engagement: Projects may overlook the importance of identifying and involving all relevant stakeholders, including those most affected by the problem. This can result in limited buy-in, reduced effectiveness, and sustainability challenges. Limited integration of cross-cutting issues: Gender, disability, and social inclusion considerations are sometimes insufficiently addressed in project design, which can undermine the project's relevance and impact for marginalized groups. Unrealistic targets and indicators: Targets may be set without a clear baseline or may not be achievable within the project timeframe and resources. Indicators may lack specificity or not align with the intended outcomes, making it hard to track progress. Insufficient risk analysis and mitigation planning: Projects may not adequately identify potential risks or develop robust mitigation strategies, leaving them vulnerable to unforeseen challenges. Lessons from previous projects not incorporated: There is often a lack of systematic use of findings and recommendations from past evaluations to inform new project designs, leading to repeated mistakes or missed opportunities for improvement. These weaknesses are typically identified in the "lessons learned" sections of project documents and are used to inform improvements in future project design, results frameworks, and cross-cutting approaches. Addressing these issues is crucial for enhancing project effectiveness, sustainability, and impact. Sources: ​generic_project_document_guidelines_final.docx​ project_final_report_0.docx Confidence: High | E17: Keeps saying Reponse time -1s? | F17: Yes | I17: Yes | J17: 46189 | K17: 1s | M17: Routes to Programme Development with topic_area=projects_evaluations.
A18: Happy path - sustainability recommendations [Evaluation] | B18: =_xlfn.TEXTBEFORE(_xlfn.TEXTAFTER(A18,"[",-1),"]") -> Evaluation | C18: What have previous evaluations found about partnerships? | D18: Same as other no-answers | E18: Will just refer to this response as "same" moving forward; timer still an issue | F18: No | I18: n/a | J18: 46189 | K18: 1s | M18: Routes to Programme Development with topic_area=projects_evaluations.
A19: Happy path - Programme Development CD Strategy [PD] | B19: =_xlfn.TEXTBEFORE(_xlfn.TEXTAFTER(A19,"[",-1),"]") -> PD | C19: What do evaluations recommend about sustainability? | D19: Same | E19: Checked "project evaluations" knowledge folder | F19: No | I19: n/a | J19: 46189 | M19: Routes to Programme Development with topic_area=projects_evaluations.
A20: Happy path - Programme Development Steering Committee [PD] | B20: =_xlfn.TEXTBEFORE(_xlfn.TEXTAFTER(A20,"[",-1),"]") -> PD | C20: What is DESA's capacity development strategy? | D20: Same | E20: Seems like correct routing? | F20: No | I20: n/a | J20: 46189 | M20: Routes to Formulate Response Programme Development with topic_area=cd_strategy.
A21: Happy path - Programme Development TAG [PD] | B21: =_xlfn.TEXTBEFORE(_xlfn.TEXTAFTER(A21,"[",-1),"]") -> PD | C21: What has the Steering Committee discussed about programme development? | D21: Same | E21: Checked knowledge folder, not empty; seems like most prog dev questions can't be found and show "-1s" response times? | F21: No | I21: n/a | J21: 46189 | M21: Routes to Programme Development with topic_area=steering_committee.
A22: Happy path - Programme Development general [PD] | B22: =_xlfn.TEXTBEFORE(_xlfn.TEXTAFTER(A22,"[",-1),"]") -> PD | C22: What are the TAG meeting materials about? | D22: Same | F22: No | I22: n/a | J22: 46189 | M22: Routes to Programme Development with topic_area=tag_meetings.
A23: Happy path - Programme Development annual progress report template [PD] | B23: =_xlfn.TEXTBEFORE(_xlfn.TEXTAFTER(A23,"[",-1),"]") -> PD | C23: What guidance exists on programme development in Cidy? | D23: Same | E23: Goes to about cidy, not form prog dev | F23: No | I23: n/a | J23: 46189 | M23: Routes to Programme Development with topic_area=general.
A24: Happy path - Programme Development final report template [PD] | B24: =_xlfn.TEXTBEFORE(_xlfn.TEXTAFTER(A24,"[",-1),"]") -> PD | C24: What instructions apply to the 2025 annual progress report template? | D24: Same | F24: No | I24: n/a | J24: 46189 | M24: Routes to Programme Development with topic_area=guidelines_templates.
A25: Happy path - Programme Development project document preparation [PD] | B25: =_xlfn.TEXTBEFORE(_xlfn.TEXTAFTER(A25,"[",-1),"]") -> PD | C25: What should be included in the final report template for a capacity development project? | D25: Answer: A final report template for a capacity development project should include the following key sections: Key Project Features Project title Project code Lead implementing entity Start and end dates (original and actual) List of beneficiary countries Implementing partners (UN system and other partners, excluding beneficiary governments) Narrative of Results Overview of results (max. 2 pages) Success story and photos (max. 300 words) Detailed Review of Achievements and Implementation Table reviewing performance indicators: expected accomplishments, baseline (T0), actual measure at project end (T1), and comments on progress Table reviewing activities: list of activities implemented, comments on variations from project design Table of deliverables: categories (e.g., workshops, training events, policies, studies, reports, toolkits), and their numbers at national, regional, and global/interregional levels Challenges Encountered and Actions Taken Table describing challenges faced and actions taken to address them Good Practices, Innovative Approaches, and Key Lessons Learned Description of effective practices and lessons for future programming Sustainability Explanation of how achievements are likely to be sustained beyond project completion Replication of Project Activities and Multiplier Effects Information on replication or plans for replication in other countries or contexts Supplementary Funding Table of financial leveraging: source/donor, purpose, year, amount raised (cash and in-kind), and description Additional Information Any other relevant information (e.g., media coverage, publications, links) Financial Information Table summarizing budget/allotment, revisions, explanations, and total expenditure by category (e.g., staff costs, consultants, travel, contractual services, operating expenses, supplies, equipment, workshops/study tours, total) This structure ensures comprehensive reporting on project implementation, results, challenges, sustainability, and financials, supporting accountability and institutional learning for future projects. Sources: ​project_final_report_0.docx​ ​generic_project_document_guidelines_final.docx​ Confidence: High | E25: This one is able to be found | F25: Yes | I25: Yes | J25: 46189 | K25: 192s | M25: Routes to Programme Development with topic_area=guidelines_templates.
A26: Happy path - Programme Development implementing partner agreement [PD] | B26: =_xlfn.TEXTBEFORE(_xlfn.TEXTAFTER(A26,"[",-1),"]") -> PD | C26: What guidance is available for preparing a project document, including theory of change, risks, workplan, and budget justification? | D26: Answer: The latest available general guidance for preparing a project document for UN Development Account-style projects includes the following key sections: Theory of Change Provide a narrative explaining how the project’s outputs and outcomes will lead to the desired change, identifying the main assumptions behind these causal links. Use “if, then, because” statements to clarify the logic (e.g., “If capacity is strengthened, then outcomes will improve, because stakeholders will have the necessary skills.”). Address how the project will promote social inclusion, gender equality, and address the needs of marginalized groups. Clearly state the evidence or rationale for selecting specific outputs and how they address root causes of the problem. Identify and review assumptions, and adjust outputs/outcomes if faulty assumptions are found. Risk Assessment Analyze possible risks that may affect project success, including external factors (e.g., political instability). For each risk, specify corresponding mitigation actions or corrective measures. Present risks and mitigation actions in a table format for clarity. Workplan Develop a result-based workplan that breaks down activities, outputs, outcomes, and timelines. For each output, specify the activities, responsible parties, expected results, and delivery schedule (by year and quarter). Ensure consistency between the narrative, workplan, and budget details. Budget Justification Provide a detailed justification for each budget class, linking costs to specific project outputs. Disaggregate costs and work months by output where possible. Budget classes typically include: Staff and Other Personnel Costs (FT30_CLASS_010), Supplies, Commodities, and Materials (FT30_CLASS_130), Equipment, Vehicles, and Furniture (FT30_CLASS_135), Contractual Services (FT30_CLASS_120), Travel (FT30_CLASS_160), Transfers and Grants to Counterparts (FT30_CLASS_140), General Operating and Other Direct Costs (FT30_CLASS_125), and Indirect Support Costs (FT30_CLASS_155). Include a summary table of planned annual expenditures and cumulative financial implementation rates. This guidance is applicable to standard project document preparation and aligns with the most recent templates and instructions for UN capacity development projects. Sources: ​generic_project_document_guidelines_final.docx​ Confidence: High | E26: ********Response time says 898 seconds, is it carrying over from the question before? | F26: Yes | I26: Yes | J26: 46189 | K26: something wrong | M26: Routes to Programme Development with topic_area=guidelines_templates.
A27: Happy path - Programme Development grants due diligence [PD] | B27: =_xlfn.TEXTBEFORE(_xlfn.TEXTAFTER(A27,"[",-1),"]") -> PD | C27: When should DESA use an implementing partner agreement instead of procurement? | D27: Answer: DESA should use an implementing partner (IP) agreement instead of procurement when the primary objective is to work jointly with another partner to achieve shared development objectives, rather than simply purchasing a product or service from the market. The key distinctions are: Use an Implementing Partner Agreement when: The UN is primarily interested in collaborating to implement an activity or set of activities that deliver on its programme of work. The focus is on achieving development results in line with the UN’s objectives, and the partner may also be a beneficiary of UN capacity development support. The UN is interested in the results and performance of a joint project and may want input or control over the process. The UN reimburses actual costs and monitors the partner’s performance, with the right to audit the partner’s accounts. The activity furthers the mandate and objectives of the partner, who may contribute resources (e.g., staff time, follow-up). Use Procurement when: The UN is obtaining a product or service for which a commercial market exists (e.g., meeting facilities, printing, professional services). The main interest is best value for money, purchased in a transparent and competitive manner. The vendor is responsible for delivering the product or service, and the UN does not audit the vendor’s accounts. The UN pays for the product or service, and the vendor requires full reimbursement of all costs incurred. Key Policy Points: The decision does not depend solely on the type of organization (government, intergovernmental, non-governmental, not-for-profit), but on whether the UN is purchasing a market-based product/service or working jointly towards shared objectives. For most DESA work with government and intergovernmental partners, the IP modality is expected. Selecting the correct modality for non-governmental partners requires careful analysis. A reference table in the guidelines further illustrates which types of activities normally fit each modality (e.g., national execution of a development project typically uses IP, while construction services use procurement). Sources: ​desa_interim_ip_and_grants_guidelines_25_september_2018.docx​ ​annexes_ipg_guidelines_25_september_2018_approved.docx​ Confidence: Very High | E27: Has to be accumulating the time, now > 1000s | F27: Yes | I27: Yes | J27: 46189 | M27: Routes to Programme Development with topic_area=implementing_partners_grants.
A28: Happy path - Programme Development IPGC templates [PD] | B28: =_xlfn.TEXTBEFORE(_xlfn.TEXTAFTER(A28,"[",-1),"]") -> PD | C28: What due diligence is required before approving a grant to an implementing partner? | D28: Answer: Before approving a grant to an implementing partner, DESA requires a comprehensive due diligence process, which may be adjusted based on the funding stream and organizational policy. The key steps and requirements include: Completion of a Due Diligence Questionnaire: The requesting Division must complete a due diligence questionnaire for all proposed implementing partners or grantees. This covers legal status, financial management, delivery capacity, project management tools, risk of fraud, and compliance with special funding conditions. For non-government organizations, additional questions address public interest objectives, affiliations with the private sector, reputational risks, and the rationale for partner selection after considering alternatives. Comparative Review: As much as possible, a comparative review of at least three organizations should be conducted to ensure open and transparent selection, unless a specific partner is requested by a donor, in which case early referral to CDO is required for due diligence. Risk Assessment: The Division must assess the partner’s capacity and past performance, including audits, assurance activities, and programme monitoring, especially when executing activities at the country level. Documentation and Verification: Legal status documents, financial statements, and evidence of sound financial management must be reviewed. Checks against Security Council sanctions, World Bank ineligible lists, and the UN List of Suspended and Removed Vendors are required. Assessment of Safeguards: The partner’s capacity to prevent or mitigate risks such as sexual exploitation and abuse must be evaluated, including evidence of regular training and policies. Conflict of Interest and Framework Agreements: Any real or potential conflicts of interest must be disclosed. If a framework partnership agreement exists, it should be consulted. Funding Stream-Specific Requirements: The due diligence process must ensure compliance with any special conditions or limitations of the funding source, such as donor-imposed requirements or restrictions on indirect costs. Submission and Review: The completed due diligence questionnaire and draft agreement are submitted to the Capacity Development Office (CDO) for review and coordination with the Implementing Partner and Grantee Committee (IPGC), which focuses on reputational and significant risks, and ensures the process was open and alternatives considered. Approval: The IPGC makes a recommendation, and the agreement is signed by the Chief, CDO, or cleared for signature by another DESA official. This process ensures that all grants and implementing partner agreements are subject to rigorous vetting, risk assessment, and compliance with both UN and donor requirements before approval. Requirements may be further tailored based on the specific funding stream or organizational policy in place at the time of the grant. Sources: ​desa_interim_ip_and_grants_guidelines_25_september_2018.docx​ ​annexes_ipg_guidelines_25_september_2018_approved.docx​ Confidence: High Answer: Before approving a grant to an implementing partner, DESA requires a comprehensive due diligence process, which may be adjusted based on the funding stream and organizational policy. The key steps and requirements include: Completion of a Due Diligence Questionnaire: The requesting Division must complete a due diligence questionnaire for all proposed implementing partners or grantees. This covers legal status, financial management, delivery capacity, project management tools, risk of fraud, and compliance with special funding conditions. For non-government organizations, additional questions address public interest objectives, affiliations with the private sector, reputational risks, and the rationale for partner selection after considering alternatives. Comparative Review: As much as possible, a comparative review of at least three organizations should be conducted to ensure open and transparent selection, unless a specific partner is requested by a donor, in which case early referral to CDO is required for due diligence. Risk Assessment: The Division must assess the partner’s capacity and past performance, including audits, assurance activities, and programme monitoring, especially when executing activities at the country level. Documentation and Verification: Legal status documents, financial statements, and evidence of sound financial management must be reviewed. Checks against Security Council sanctions, World Bank ineligible lists, and the UN List of Suspended and Removed Vendors are required. Assessment of Safeguards: The partner’s capacity to prevent or mitigate risks such as sexual exploitation and abuse must be evaluated, including evidence of regular training and policies. Conflict of Interest and Framework Agreements: Any real or potential conflicts of interest must be disclosed. If a framework partnership agreement exists, it should be consulted. Funding Stream-Specific Requirements: The due diligence process must ensure compliance with any special conditions or limitations of the funding source, such as donor-imposed requirements or restrictions on indirect costs. Submission and Review: The completed due diligence questionnaire and draft agreement are submitted to the Capacity Development Office (CDO) for review and coordination with the Implementing Partner and Grantee Committee (IPGC), which focuses on reputational and significant risks, and ensures the process was open and alternatives considered. Approval: The IPGC makes a recommendation, and the agreement is signed by the Chief, CDO, or cleared for signature by another DESA official. This process ensures that all grants and implementing partner agreements are subject to rigorous vetting, risk assessment, and compliance with both UN and donor requirements before approval. Requirements may be further tailored based on the specific funding stream or organizational policy in place at the time of the grant. Sources: ​desa_interim_ip_and_grants_guidelines_25_september_2018.docx​ ​annexes_ipg_guidelines_25_september_2018_approved.docx​ Confidence: High Answer: Before approving a grant to an implementing partner, DESA requires a comprehensive due diligence process, which may be adjusted based on the funding stream and organizational policy. The key steps and requirements include: Completion of a Due Diligence Questionnaire: The requesting Division must complete a due diligence questionnaire for all proposed implementing partners or grantees. This covers legal status, financial management, delivery capacity, project management tools, risk of fraud, and compliance with special funding conditions. For non-government organizations, additional questions address public interest objectives, affiliations with the private sector, reputational risks, and the rationale for partner selection after considering alternatives. Comparative Review: As much as possible, a comparative review of at least three organizations should be conducted to ensure open and transparent selection, unless a specific partner is requested by a donor, in which case early referral to CDO is required for due diligence. Risk Assessment: The Division must assess the partner’s capacity and past performance, including audits, assurance activities, and programme monitoring, especially when executing activities at the country level. Documentation and Verification: Legal status documents, financial statements, and evidence of sound financial management must be reviewed. Checks against Security Council sanctions, World Bank ineligible lists, and the UN List of Suspended and Removed Vendors are required. Assessment of Safeguards: The partner’s capacity to prevent or mitigate risks such as sexual exploitation and abuse must be evaluated, including evidence of regular training and policies. Conflict of Interest and Framework Agreements: Any real or potential conflicts of interest must be disclosed. If a framework partnership agreement exists, it should be consulted. Funding Stream-Specific Requirements: The due diligence process must ensure compliance with any special conditions or limitations of the funding source, such as donor-imposed requirements or restrictions on indirect costs. Submission and Review: The completed due diligence questionnaire and draft agreement are submitted to the Capacity Development Office (CDO) for review and coordination with the Implementing Partner and Grantee Committee (IPGC), which focuses on reputational and significant risks, and ensures the process was open and alternatives considered. Approval: The IPGC makes a recommendation, and the agreement is signed by the Chief, CDO, or cleared for signature by another DESA official. This process ensures that all grants and implementing partner agreements are subject to rigorous vetting, risk assessment, and compliance with both UN and donor requirements before approval. Requirements may be further tailored based on the specific funding stream or organizational policy in place at the time of the grant. Sources: ​desa_interim_ip_and_grants_guidelines_25_september_2018.docx​ ​annexes_ipg_guidelines_25_september_2018_approved.docx​ Confidence: High | E28: n/a | F28: Yes | I28: Yes | J28: 46189 | K28: minus 1 | M28: Routes to Programme Development with topic_area=implementing_partners_grants.
A29: Happy path - RPTC budget and finance [RPTC] | B29: =_xlfn.TEXTBEFORE(_xlfn.TEXTAFTER(A29,"[",-1),"]") -> RPTC | C29: Where can I find the IPGC decision template and partner evaluation template for grants? | D29: Answer: The official IPGC (Implementing Partner and Grantee Committee) decision template and the partner evaluation template required for grants within DESA’s implementing partners and grants procedures are provided in the annexes to the DESA Interim Guidelines on IPs and Grants (version 25 September 2018). Specifically: The IPGC decision template is found in Annex 4. It includes fields for the date of meeting, implementing partner or grantee, amount of fund transfer, recommendation status (recommended, not recommended, or returned for additional information), committee member signatures, and a brief statement of reasons or dissenting opinions. It also includes a section for approval by the Under-Secretary-General or delegated official. The partner evaluation template is found in Annex 5. This template is used to assess whether the implementing partner or grantee delivered the activities covered by the agreement, their effectiveness, timeliness, quality of implementation, quality of financial and substantive reports, and any concerns about possible fraud or mismanagement. It includes rating scales and space for comments, as well as staff and division director sign-off. Both templates are part of the annexes file that accompanies the main guidelines and are referenced as required operational tools for DESA’s grants and implementing partner agreements procedures. These annexes are available in the document titled "annexes_ipg_guidelines_25_september_2018_approved.docx". Sources: ​annexes_ipg_guidelines_25_september_2018_approved.docx​ Confidence: Very High | E29: n/a | F29: Yes | I29: Yes | J29: 46189 | K29: not noting moving forward until fix | M29: Routes to Programme Development with topic_area=implementing_partners_grants.
A30: Happy path - RPTC governance [RPTC] | B30: =_xlfn.TEXTBEFORE(_xlfn.TEXTAFTER(A30,"[",-1),"]") -> RPTC | C30: What are the RPTC budget and finance requirements? | D30: Same | E30: Not showing timer debug; same as before with programme dev? | F30: No | I30: n/a | J30: 46189 | K30: not showing | M30: Routes to Formulate Response RPTC with topic_area=rptc_guidance_templates.
A31: Happy path - RPTC roles [RPTC] | B31: =_xlfn.TEXTBEFORE(_xlfn.TEXTAFTER(A31,"[",-1),"]") -> RPTC | C31: What are the RPTC governance arrangements? | D31: Same | F31: No | I31: n/a | J31: 46189 | M31: Routes to Formulate Response RPTC with topic_area=rptc_guidance_templates.
A32: Happy path - RPTC programme design standards [RPTC] | B32: =_xlfn.TEXTBEFORE(_xlfn.TEXTAFTER(A32,"[",-1),"]") -> RPTC | C32: What are RPTC roles and responsibilities? | D32: Same | F32: No | I32: n/a | J32: 46189 | M32: Routes to Formulate Response RPTC with topic_area=rptc_guidance_templates.
A33: Happy path - RPTC evaluation criteria [RPTC] | B33: =_xlfn.TEXTBEFORE(_xlfn.TEXTAFTER(A33,"[",-1),"]") -> RPTC | C33: What programme design standards apply to RPTC? | D33: Same | F33: No | I33: n/a | J33: 46189 | M33: Routes to Formulate Response RPTC with topic_area=rptc_guidance_templates.
A34: Happy path - RPTC reports [RPTC] | B34: =_xlfn.TEXTBEFORE(_xlfn.TEXTAFTER(A34,"[",-1),"]") -> RPTC | C34: What are the RPTC evaluation criteria? | D34: Same | F34: No | I34: n/a | J34: 46189 | M34: Routes to Formulate Response RPTC with topic_area=rptc_guidance_templates.
A35: Happy path - PDF / UNPDF [PDF] | B35: =_xlfn.TEXTBEFORE(_xlfn.TEXTAFTER(A35,"[",-1),"]") -> PDF | C35: Where can I find guidance on RPTC reports? | D35: Same | F35: No | I35: n/a | J35: 46189 | M35: Routes to Formulate Response RPTC with topic_area=rptc_guidance_templates.
A36: Happy path - About Cidy [About Cidy] | B36: =_xlfn.TEXTBEFORE(_xlfn.TEXTAFTER(A36,"[",-1),"]") -> About Cidy | C36: What does the UNPDF guidance say about reporting? | D36: Same | F36: No | I36: n/a | J36: 46189 | M36: Routes to Formulate Response PDF or the temporary not-yet-developed PDF message.
A37: Happy path - About Cidy coverage [About Cidy] | B37: =_xlfn.TEXTBEFORE(_xlfn.TEXTAFTER(A37,"[",-1),"]") -> About Cidy | C37: How does Cidy work? | D37: Answer: Cidy is an AI-enabled knowledge assistant specifically designed to support UN DESA’s capacity-development work. Its core functionality is to help staff efficiently find, interpret, draft, and apply approved internal guidance throughout the capacity-development project lifecycle. Here’s how Cidy operates: Governed Service Layer: Cidy functions as a governed service over curated CDPMO knowledge, project workflows, templates, reporting rules, escalation paths, and feedback loops. Intent Classification: When a user asks a capacity-development question, Cidy classifies the intent of the query and only requests clarification if necessary. Targeted Search: It searches the most relevant, approved knowledge sources to draft a grounded answer. Confidence Assessment: Cidy assesses the confidence of its response, shares sources, and collects feedback or escalates the query to a human expert if the answer is low-confidence, incomplete, or out of scope. Guidance Delivery: It routes questions to the correct knowledge domain (e.g., Development Account, RPTC, Programme Development, or general CDPMO guidance), explains procedures, supports project lifecycle work, and points users to the right templates and quality checks. Institutional Memory: Cidy captures recurring questions and unresolved issues to improve the knowledge base over time. Escalation Path: If Cidy cannot provide a satisfactory answer, it offers a path for human follow-up. Cidy is distinct from general-purpose chatbots because it uses only curated, approved institutional knowledge, classifies and enriches user requests, aims for source-grounded answers, and is designed with governance, feedback, and human-in-the-loop support. It is not a replacement for staff judgment or formal approvals and does not function as a general internet search tool. Cidy is currently an active prototype or developing institutional service, not a fully mature production system across all domains. Sources: ​Cidy - What It Does.docx​ Confidence: Very High | E37: Still missing debug timer -- old agent version? | F37: Yes | I37: Yes | J37: 46189 | M37: Routes to Formulate Response Cidy About with topic_area=about_cidy. No clarification should be required.
A38: Happy path - About Cidy maintenance [About Cidy] | B38: =_xlfn.TEXTBEFORE(_xlfn.TEXTAFTER(A38,"[",-1),"]") -> About Cidy | C38: What knowledge sources does Cidy currently use? | D38: Answer: Cidy, the UN DESA Capacity Development Programme Management Office (CDPMO) knowledge assistant, uses a curated set of internal, approved knowledge sources specifically selected for capacity-development work. These sources are organized into knowledge domains and topic areas, each mapped to specific response files (YAMLs) that determine which knowledge folders or documents are searched. The main domains currently covered include: Development Account (DA): Project planning/design, evaluation design, and general guidance, with mapped folders for each topic area. Regular Programme of Technical Cooperation (RPTC): Guidance/templates and progress reports, with many topic labels mapped as aliases to these sources. Programme Development: Includes steering committee records, TAG meetings, project evaluations, guidelines/templates, implementing partners/grants, Resident Coordinator engagement, and strategic documents. These are marked for review as the knowledge base matures. General CDPMO: A general knowledge folder mapped for broad or unclassified questions. Peace and Development Trust Fund / UNPDF and About Cidy: These domains are recognized but currently lack mapped knowledge folders or response files. Cidy does not use general internet sources; it is anchored in official DESA/CDPMO materials to ensure answers are grounded in institutional guidance. When a specific topic area is not matched, fallback sources are used as safety nets, but these should not be confused with primary topic coverage. The knowledge base is actively maintained and updated, with some areas marked as requiring further validation or development as the system matures. Sources: ​Cidy - Topics Covered.docx​ Confidence: Very High | F38: Yes | I38: Yes | J38: 46189 | M38: Routes to Formulate Response Cidy About with topic_area=about_cidy.
A39: Clarification path - fund to DA [DA] | B39: =_xlfn.TEXTBEFORE(_xlfn.TEXTAFTER(A39,"[",-1),"]") -> DA | C39: Who maintains Cidy's knowledge? | D39: Answer: The responsibility for maintaining Cidy's knowledge base and ensuring its information is up to date lies with the Knowledge Control Center. This component tracks knowledge folders, source-use instructions, manager updates, route coverage, and YAML work needed to keep response topics aligned. The governance and maintenance architecture also includes an inventory generator, refresh workflow, and structural test runner to support ongoing updates and quality control. Human-in-the-loop processes are in place for unresolved or low-confidence cases, which are routed to feedback or escalation rather than being treated as definitive answers. This ensures that the knowledge base remains current and reliable as the system matures and new materials are added or updated. Sources: ​Cidy - Architecture.docx​ Confidence: Very High | E39: Is this correct? | F39: Yes | I39: Yes | J39: 46189 | M39: Routes to Formulate Response Cidy About with topic_area=about_cidy.
A40: Clarification path - fund to RPTC [RPTC] | B40: =_xlfn.TEXTBEFORE(_xlfn.TEXTAFTER(A40,"[",-1),"]") -> RPTC | C40: How do I write an evaluation report? | D40: Same | E40: Did get asked multiple choice; DEBUG - Pass 2 result: Broad DA source (Pass 1 was blank) Query sent: Response: | F40: No | I40: n/a | J40: 46189 | L40: Development Account (DA) | M40: Classifier asks fund clarification. Clarifier maps Development Account (DA) to knowledge_domain=da, funding_stream=DA, topic_area=evaluation_design, intentStatus=ready_to_route. Router routes to Formulate Response DA.
A41: Clarification path - fund to PDF [PDF] | B41: =_xlfn.TEXTBEFORE(_xlfn.TEXTAFTER(A41,"[",-1),"]") -> PDF | C41: What are the reporting requirements? | L41: RPTC | M41: Classifier asks fund clarification. Clarifier maps to knowledge_domain=rptc, funding_stream=RPTC. Router routes to RPTC or temporary not-yet-developed RPTC message.
A42: Clarification path - fund not sure [Not Sure] | B42: =_xlfn.TEXTBEFORE(_xlfn.TEXTAFTER(A42,"[",-1),"]") -> Not Sure | C42: Which reporting template should I use? | L42: UNPDF / PDF | M42: Classifier asks fund or artifact clarification. After UNPDF/PDF selection, Clarifier maps to knowledge_domain=pdf, funding_stream=PDF. Router routes to PDF or temporary not-yet-developed message.
A43: Clarification path - domain to DA [Not Sure] | B43: =_xlfn.TEXTBEFORE(_xlfn.TEXTAFTER(A43,"[",-1),"]") -> Not Sure | C43: Are travel costs eligible? | L43: Not sure | M43: Classifier asks fund clarification. Clarifier maps Not sure to general_cd or programme_development depending configured default. Router should avoid unsafe fund-specific answer and likely route to User Feedback or general guidance.
A44: Clarification path - domain to Programme Development [Not Sure] | B44: =_xlfn.TEXTBEFORE(_xlfn.TEXTAFTER(A44,"[",-1),"]") -> Not Sure | C44: I need help with a project. Where do I start? | L44: Development Account (DA) | M44: Classifier asks domain clarification. Clarifier maps to knowledge_domain=da, funding_stream=DA, topic_area=general or project_planning_design. Router routes to Formulate Response DA.
A45: Clarification path - domain to Evaluation Evidence [Not Sure] | B45: =_xlfn.TEXTBEFORE(_xlfn.TEXTAFTER(A45,"[",-1),"]") -> Not Sure | C45: I need help with a project. Where do I start? | L45: Programme Development | M45: Clarifier maps to knowledge_domain=programme_development, funding_stream=UNCLEAR. Router routes to Programme Development.
A46: Clarification path - domain to About Cidy [Not Sure] | B46: =_xlfn.TEXTBEFORE(_xlfn.TEXTAFTER(A46,"[",-1),"]") -> Not Sure | C46: I need help understanding project performance. Where should I look? | L46: Project Evaluations / Lessons Learned | M46: Clarifier maps to knowledge_domain=programme_development, topic_area=projects_evaluations and routes to Programme Development.
A47: Clarification path - domain to RPTC [Not Sure] | B47: =_xlfn.TEXTBEFORE(_xlfn.TEXTAFTER(A47,"[",-1),"]") -> Not Sure | C47: I need help. What is this tool? | L47: About Cidy | M47: Clarifier maps to knowledge_domain=about_cidy. Router routes to Formulate Response Cidy About.
A48: Clarification path - domain typed DA [Not Sure] | B48: =_xlfn.TEXTBEFORE(_xlfn.TEXTAFTER(A48,"[",-1),"]") -> Not Sure | C48: Can you help me with a project report? | L48: RPTC | M48: Clarifier maps to knowledge_domain=rptc, funding_stream=RPTC. Router routes to RPTC.
A49: Clarification path - domain typed Development Account [Not Sure] | B49: =_xlfn.TEXTBEFORE(_xlfn.TEXTAFTER(A49,"[",-1),"]") -> Not Sure | C49: Can you help me with a project? | L49: DA | M49: Typed answer DA should normalize to knowledge_domain=da and funding_stream=DA. Router routes to DA.
A50: Clarification path - domain typed UNPDF [Not Sure] | B50: =_xlfn.TEXTBEFORE(_xlfn.TEXTAFTER(A50,"[",-1),"]") -> Not Sure | C50: Can you help me with a project? | L50: Development Account | M50: Typed answer should normalize to DA. Router routes to Formulate Response DA.
A51: Clarification path - artifact concept note [Not Sure] | B51: =_xlfn.TEXTBEFORE(_xlfn.TEXTAFTER(A51,"[",-1),"]") -> Not Sure | C51: What guidance applies to this project? | L51: UNPDF | M51: Typed answer should normalize to knowledge_domain=pdf, funding_stream=PDF.
A52: Clarification path - artifact evaluation report [Not Sure] | B52: =_xlfn.TEXTBEFORE(_xlfn.TEXTAFTER(A52,"[",-1),"]") -> Not Sure | C52: Where is the template? | L52: Concept note | M52: Classifier asks artifact clarification. Clarifier maps topic_area=project_planning_design. If funding stream remains unclear, it may ask a second fund clarification or route to Programme Development/general depending configuration.
... A56: Clarification path - max attempts dead end [Not Sure] | B56: =_xlfn.TEXTBEFORE(_xlfn.TEXTAFTER(A56,"[",-1),"]") -> Not Sure | C56: Which template should I use? | L56: Attempt 1: something invalid. Attempt 2: Development Account (DA). | M56: Clarifier increments attempts, reprompts once, then maps DA correctly and routes to Formulate Response DA before max attempts is exceeded.
A57: Vague path - domain clarification [Not Sure] | B57: =_xlfn.TEXTBEFORE(_xlfn.TEXTAFTER(A57,"[",-1),"]") -> Not Sure | C57: Where do I start? | D57: Matches expected behavior: Status: needs_clarification | Domain: unclear | Funding stream: UNCLEAR | Topic area: unclear | Requires clarification: Yes | Clarification type: domain | M57: Classifier should not route directly. It should set requires_clarification=Yes, clarification_type=domain.
A58: Vague path - template clarification [Not Sure] | B58: =_xlfn.TEXTBEFORE(_xlfn.TEXTAFTER(A58,"[",-1),"]") -> Not Sure | C58: I need a template. | D58: Asks for artifact clarification, but when selecting "project document" it then just goes to search even though It would need further clarification | F58: no | H58: low | I58: No Sources Found | M58: Classifier should ask artifact or fund clarification, not search knowledge directly.
A59: Vague path - report clarification [Not Sure] | B59: =_xlfn.TEXTBEFORE(_xlfn.TEXTAFTER(A59,"[",-1),"]") -> Not Sure | C59: Can you help me write the report? | D59: Asks for domain clarification, when selecting "DA", result is BLANK | M59: Classifier should ask artifact and/or fund clarification. It should not route until enough information is available.
A60: Vague path - guidance clarification [Not Sure] | B60: =_xlfn.TEXTBEFORE(_xlfn.TEXTAFTER(A60,"[",-1),"]") -> Not Sure | C60: What guidance is available? | D60: Asks for domain clarification, when selecting "project eval…", then "Answer: I was not able to find information in my knowledge sources that could answer this question." | M60: Classifier should ask domain clarification because the domain is unclear.
A61: Vague path - project support clarification [Not Sure] | B61: =_xlfn.TEXTBEFORE(_xlfn.TEXTAFTER(A61,"[",-1),"]") -> Not Sure | C61: Can Cidy help me with my project? | D61: Answer: Cidy is designed to provide support and guidance for UN DESA capacity-development work, regardless of whether the project type or funding stream is specified. Its core function is to help staff find, interpret, draft, and apply approved internal guidance across the capacity-development project lifecycle. Cidy routes questions to the most relevant knowledge domain, explains procedures, supports project lifecycle work (including design, formulation, implementation, monitoring, evaluation, reporting, lessons learned, and closure), and points users to the correct concepts, templates, and quality checks. It operates as a governed service layer over curated CDPMO knowledge, project workflows, templates, reporting rules, escalation paths, and feedback loops. If the information provided is insufficient or ambiguous, Cidy will classify the request, seek clarification only when necessary, and escalate to human follow-up if the answer is low-confidence, incomplete, or out of scope. This ensures you receive actionable guidance even when project specifics are not fully defined. | F61: Yes | H61: Very High | I61: Yes | J61: 46189 | M61: Classifier should ask domain clarification or route to About Cidy depending model judgment; should not fabricate a specific fund.
A62: Out of scope - weather [OOS] | B62: =_xlfn.TEXTBEFORE(_xlfn.TEXTAFTER(A62,"[",-1),"]") -> OOS | C62: What is the weather in New York today? | D62: Cidy is designed to support DESA capacity-development knowledge, including DA, RPTC, UNPDF/PDF, Programme Development, Project Evaluation evidence, and Cidy-related guidance. This question appears outside that scope. | F62: Yes | H62: Pass | M62: Classifier sets knowledge_domain=out_of_scope, requires_clarification=No. Router sends controlled scope message and routes to User Feedback.
A63: Out of scope - sports [OOS] | B63: =_xlfn.TEXTBEFORE(_xlfn.TEXTAFTER(A63,"[",-1),"]") -> OOS | C63: Who won the last World Cup? | D63: Cidy is designed to support DESA capacity-development knowledge, including DA, RPTC, UNPDF/PDF, Programme Development, Project Evaluation evidence, and Cidy-related guidance. This question appears outside that scope. | F63: Yes | H63: Pass | M63: Routes to User Feedback as out_of_scope. No clarification should be asked.
A64: Out of scope - poem [OOS] | B64: =_xlfn.TEXTBEFORE(_xlfn.TEXTAFTER(A64,"[",-1),"]") -> OOS | C64: Write me a poem about cats. | D64: Cidy is designed to support DESA capacity-development knowledge, including DA, RPTC, UNPDF/PDF, Programme Development, Project Evaluation evidence, and Cidy-related guidance. This question appears outside that scope. | F64: Yes | H64: Pass | M64: Routes to User Feedback as out_of_scope. No knowledge search.
A65: Out of scope - laptop help [OOS] | B65: =_xlfn.TEXTBEFORE(_xlfn.TEXTAFTER(A65,"[",-1),"]") -> OOS | C65: How do I fix my laptop screen? | D65: Cidy is designed to support DESA capacity-development knowledge, including DA, RPTC, UNPDF/PDF, Programme Development, Project Evaluation evidence, and Cidy-related guidance. This question appears outside that scope. | F65: Yes | H65: Pass | M65: Routes to User Feedback as out_of_scope.
A66: Out of scope - stock investment [OOS] | B66: =_xlfn.TEXTBEFORE(_xlfn.TEXTAFTER(A66,"[",-1),"]") -> OOS | C66: What stock should I buy this week? | D66: Cidy is designed to support DESA capacity-development knowledge, including DA, RPTC, UNPDF/PDF, Programme Development, Project Evaluation evidence, and Cidy-related guidance. This question appears outside that scope. | F66: Yes | H66: Pass | M66: Routes to User Feedback as out_of_scope.
A67: Happy path - RPTC activity proposal template [RPTC] | B67: =_xlfn.TEXTBEFORE(_xlfn.TEXTAFTER(A67,"[",-1),"]") -> RPTC | C67: What information is required in an RPTC activity proposal template? | D67: I was not able to find information in my knowledge sources that could answer this question. | F67: no | H67: Low | I67: no | M67: Routes to Formulate Response RPTC with topic_area=rptc_guidance_templates. | N67: 2026-05-26
A68: Happy path - RPTC common reporting standards [RPTC] | B68: =_xlfn.TEXTBEFORE(_xlfn.TEXTAFTER(A68,"[",-1),"]") -> RPTC | C68: What are the common reporting standards and minimum data points for RPTC activities? | D68: I was not able to find information in my knowledge sources that could answer this question. | F68: no | H68: Low | I68: no | M68: Routes to Formulate Response RPTC with topic_area=rptc_guidance_templates. | N68: 2026-05-26
A69: Happy path - RPTC IRA guidance [RPTC] | B69: =_xlfn.TEXTBEFORE(_xlfn.TEXTAFTER(A69,"[",-1),"]") -> RPTC | C69: What guidance applies to Inter-Regional Adviser recruitment, renewal, reporting lines, and administration? | D69: I was not able to find information in my knowledge sources that could answer this question. | F69: no | H69: Low | I69: no | M69: Routes to Formulate Response RPTC with topic_area=rptc_guidance_templates. | N69: 2026-05-26
A70: Happy path - RPTC activity report template [RPTC] | B70: =_xlfn.TEXTBEFORE(_xlfn.TEXTAFTER(A70,"[",-1),"]") -> RPTC | C70: What should be captured in an RPTC activity report template after an activity? | D70: I was not able to find information in my knowledge sources that could answer this question. | F70: no | H70: Low | I70: no | M70: Routes to Formulate Response RPTC with topic_area=rptc_guidance_templates. | N70: 2026-05-26
A71: Happy path - RPTC planning and approval process [RPTC] | B71: =_xlfn.TEXTBEFORE(_xlfn.TEXTAFTER(A71,"[",-1),"]") -> RPTC | C71: How are RPTC activities planned, approved, revised, and reported after completion? | D71: I was not able to find information in my knowledge sources that could answer this question. | F71: no | H71: Low | I71: no | M71: Routes to Formulate Response RPTC with topic_area=rptc_guidance_templates. | N71: 2026-05-26
A72: Happy path - RPTC 2024 achievements [RPTC] | B72: =_xlfn.TEXTBEFORE(_xlfn.TEXTAFTER(A72,"[",-1),"]") -> RPTC | C72: What were the main achievements of the Regular Programme of Technical Cooperation in 2024? | D72: I was not able to find information in my knowledge sources that could answer this question. | F72: no | H72: Low | I72: no | M72: Routes to Formulate Response RPTC with topic_area=rptc_progress_reports. | N72: 2026-05-26
A73: Happy path - RPTC 2024 countries requests interventions [RPTC] | B73: =_xlfn.TEXTBEFORE(_xlfn.TEXTAFTER(A73,"[",-1),"]") -> RPTC | C73: How many countries, requests, interventions, and people were supported through RPTC in 2024? | M73: Routes to Formulate Response RPTC with topic_area=rptc_progress_reports. | N73: 2026-05-26
A74: Happy path - RPTC implementing entities [RPTC] | B74: =_xlfn.TEXTBEFORE(_xlfn.TEXTAFTER(A74,"[",-1),"]") -> RPTC | C74: Which UN implementing entities delivered RPTC activities, and how did their results differ? | M74: Routes to Formulate Response RPTC with topic_area=rptc_progress_reports. | N74: 2026-05-26
A75: Happy path - RPTC SIDS LDC LLDC support [RPTC] | B75: =_xlfn.TEXTBEFORE(_xlfn.TEXTAFTER(A75,"[",-1),"]") -> RPTC | C75: How did RPTC support least developed countries, landlocked developing countries, and small island developing States? | M75: Routes to Formulate Response RPTC with topic_area=rptc_progress_reports. | N75: 2026-05-26
A76: Happy path - RPTC future recommendations [RPTC] | B76: =_xlfn.TEXTBEFORE(_xlfn.TEXTAFTER(A76,"[",-1),"]") -> RPTC | C76: What challenges and recommendations does the RPTC progress report identify for strengthening future years? | M76: Routes to Formulate Response RPTC with topic_area=rptc_progress_reports. | N76: 2026-05-26
A77: Happy path - Programme Development Resident Coordinator mission notice [RPTC] | B77: =_xlfn.TEXTBEFORE(_xlfn.TEXTAFTER(A77,"[",-1),"]") -> RPTC | C77: When should DESA inform the RC or RCO about a planned country mission? | D77: Answer: When to Inform RC/RCO: DESA should inform the RC or RCO about a planned country mission whenever there is an activity, project, request, or workshop that involves direct engagement in a country, especially if it relates to capacity development, technical assistance, or any event requiring coordination with national stakeholders. This is particularly important for countries classified as SIDS (Small Island Developing States), LDC (Least Developed Countries), or LLDC (Landlocked Developing Countries), as these groupings often have specific coordination and reporting requirements. Relation to Country Records and Formats: The country card, country record, compact country file, and region/subregion identifiers (including ISO3 codes) are used to organize and track all relevant projects, requests, proposals, RPTC proposals, activities, RPTC activities, travel records, contacts, budgets, statuses, and divisions for each country. Informing the RC/RCO ensures that these records are up-to-date and that the mission is aligned with ongoing or planned activities, avoids duplication, and supports effective coordination. For example, Uganda’s country card lists active and planned projects, requests, RPTC activities, and financial metrics, and includes contacts for each activity. The RC/RCO should be informed to ensure these are reflected accurately in the country’s records and to facilitate coordination with local stakeholders. Status and Groupings: The current status of SIDS, LDC, LLDC is tracked in the country card and related files, which also indicate the relevant division (e.g., Statistics Division, Division for Public Institutions and Digital Government, Financing for Sustainable Development Office). Missions should be reported in the context of these groupings, as they may affect the nature of the support, reporting obligations, and coordination requirements. Source File Relevance: The source file (e.g., compact country filename) is the authoritative record for all country-specific activities and should be updated to reflect the planned mission, including its status, budget, participants, and contact information. Summary of Steps: Review the country card/record for current and planned activities. Identify the relevant division and contact listed for the country. Notify the RC/RCO about the planned mission, referencing the country’s grouping (SIDS, LDC, LLDC) and the specific activity/project. Update the source file to reflect the mission, including all relevant details (status, budget, participants, contacts). Ensure coordination and reporting align with the country’s current records and groupings | F77: Yes | H77: High | I77: Yes | M77: Routes to Programme Development with topic_area=resident_coordinator. | N77: 2026-05-27
A78: Happy path - Programme Development UNSDCF alignment [PD] | B78: =_xlfn.TEXTBEFORE(_xlfn.TEXTAFTER(A78,"[",-1),"]") -> PD | C78: How should DESA align country-level support with the CCA and UNSDCF processes? | D78: I was not able to find information in my knowledge sources that could answer this question. | F78: no | H78: Low | I78: no | M78: Routes to Programme Development with topic_area=resident_coordinator. | N78: 2026-05-27
A79: Happy path - Programme Development UNCT membership [PD] | B79: =_xlfn.TEXTBEFORE(_xlfn.TEXTAFTER(A79,"[",-1),"]") -> PD | C79: When can DESA become a UNCT member or UNSDCF signatory? | D79: I was not able to find information in my knowledge sources that could answer this question. | F79: no | H79: Low | I79: no | M79: Routes to Programme Development with topic_area=resident_coordinator. | N79: 2026-05-27
A80: Happy path - Programme Development strategic priorities [PD] | B80: =_xlfn.TEXTBEFORE(_xlfn.TEXTAFTER(A80,"[",-1),"]") -> PD | C80: What are DESA's main action areas for 2023? | D80: I was not able to find information in my knowledge sources that could answer this question. | F80: no | H80: Low | I80: no | M80: Routes to Programme Development with topic_area=cd_strategy. | N80: 2026-05-27
A81: Happy path - Programme Development service delivery model [PD] | B81: =_xlfn.TEXTBEFORE(_xlfn.TEXTAFTER(A81,"[",-1),"]") -> PD | C81: What are the five service lines or areas of work in DESA's capacity development strategy? | M81: Routes to Programme Development with topic_area=cd_strategy. | N81: 2026-05-27
A82: Clarification path - Programme Development strategy from broad Cidy question [Not Sure] | B82: =_xlfn.TEXTBEFORE(_xlfn.TEXTAFTER(A82,"[",-1),"]") -> Not Sure | C82: How does the knowledge hub prioritize requests? | L82: Programme Development | M82: Classifier may ask domain clarification for broad Cidy-related knowledge hub wording. Clarifier maps Programme Development and routes to Programme Development with topic_area=cd_strategy. | N82: 2026-05-27
A83: Happy path - About Cidy overview [About Cidy] | B83: =_xlfn.TEXTBEFORE(_xlfn.TEXTAFTER(A83,"[",-1),"]") -> About Cidy | C83: What is Cidy and what problem is it intended to solve? | D83: I was not able to find information in my knowledge sources that could answer this question. | F83: no | H83: Low | I83: no | M83: Intent Classifier sets knowledge_domain=about_cidy, funding_stream=UNCLEAR, topic_area=about_cidy, requires_clarification=No. Intent Router routes to Formulate Response Cidy About. | N83: 2026-05-27
A84: Happy path - About Cidy comparison [About Cidy] | B84: =_xlfn.TEXTBEFORE(_xlfn.TEXTAFTER(A84,"[",-1),"]") -> About Cidy | C84: How does Cidy differ from a general-purpose AI chatbot? | D84: I was not able to find information in my knowledge sources that could answer this question. | F84: no | H84: Low | I84: no | M84: Routes directly to Formulate Response Cidy About with topic_area=about_cidy. | N84: 2026-05-27
A85: Happy path - About Cidy coverage [About Cidy] | B85: =_xlfn.TEXTBEFORE(_xlfn.TEXTAFTER(A85,"[",-1),"]") -> About Cidy | C85: Which topics and knowledge areas does Cidy currently cover? | D85: I was not able to find information in my knowledge sources that could answer this question. | F85: no | H85: Low | I85: no | M85: Routes directly to Formulate Response Cidy About with topic_area=about_cidy. | N85: 2026-05-27
A86: Happy path - About Cidy user questions [About Cidy] | B86: =_xlfn.TEXTBEFORE(_xlfn.TEXTAFTER(A86,"[",-1),"]") -> About Cidy | C86: What kinds of DA, RPTC, Programme Development, and general CDPMO questions can users ask Cidy? | D86: I was not able to find information in my knowledge sources that could answer this question. | F86: no | H86: Low | I86: no | M86: Routes directly to Formulate Response Cidy About with topic_area=about_cidy. | N86: 2026-05-27
A87: Happy path - About Cidy prompt examples [About Cidy] | B87: =_xlfn.TEXTBEFORE(_xlfn.TEXTAFTER(A87,"[",-1),"]") -> About Cidy | C87: What are examples of good user questions for Cidy? | M87: Routes directly to Formulate Response Cidy About with topic_area=about_cidy. | N87: 2026-05-27
A88: Happy path - About Cidy routing flow [About Cidy] | B88: =_xlfn.TEXTBEFORE(_xlfn.TEXTAFTER(A88,"[",-1),"]") -> About Cidy | C88: How does Cidy classify a question and route it to the right knowledge source? | M88: Routes directly to Formulate Response Cidy About with topic_area=about_cidy. | N88: 2026-05-27
A89: Happy path - About Cidy low confidence [About Cidy] | B89: =_xlfn.TEXTBEFORE(_xlfn.TEXTAFTER(A89,"[",-1),"]") -> About Cidy | C89: What happens when Cidy is uncertain or the answer has low confidence? | M89: Routes directly to Formulate Response Cidy About with topic_area=about_cidy. | N89: 2026-05-27
A90: Happy path - About Cidy architecture [About Cidy] | B90: =_xlfn.TEXTBEFORE(_xlfn.TEXTAFTER(A90,"[",-1),"]") -> About Cidy | C90: What are the main components of Cidy's Copilot Studio architecture? | M90: Routes directly to Formulate Response Cidy About with topic_area=about_cidy. | N90: 2026-05-27
A91: Greeting path - English greeting only [Greeting] | B91: =_xlfn.TEXTBEFORE(_xlfn.TEXTAFTER(A91,"[",-1),"]") -> Greeting | C91: Hi | M91: User Inquiry greeting classifier sets isGreeting=true and routes to Greeting. Greeting sends the Cidy scope message, clears Global.userQuestion and Global.awaitingNewQuestion, then returns to User Inquiry for a fresh substantive question. It should not route the greeting to Intent. | N91: 2026-05-28
A92: Greeting path - Multilingual greeting only [Greeting] | B92: =_xlfn.TEXTBEFORE(_xlfn.TEXTAFTER(A92,"[",-1),"]") -> Greeting | C92: Bonjour | M92: User Inquiry greeting classifier sets isGreeting=true and routes to Greeting. Greeting sends the Cidy scope message, clears Global.userQuestion and Global.awaitingNewQuestion, then returns to User Inquiry for a fresh substantive question. It should not route the greeting to Intent. | N92: 2026-05-28
A93: Greeting guard - greeting plus substantive question [Greeting] | B93: =_xlfn.TEXTBEFORE(_xlfn.TEXTAFTER(A93,"[",-1),"]") -> Greeting | C93: Good morning, how do I design a DA concept note? | D93: Answer: Intent: You are seeking step-by-step guidance for drafting a Development Account (DA) concept note for project planning and design, using the most recent (19th tranche) guidelines. Step-by-Step Instructions for Designing a DA Concept Note (19th Tranche): Use the Correct Template and Guidelines Always use the separate concept note template provided for the 19th tranche to ensure all sections are in the correct format. Reference the Concept Note Guidelines for detailed instructions on each section. Main Elements to Include Your concept note must contain the following sections: Background Fascicle Note (including Title, Implementing entity and partners, Relationship to SDG targets, Objective, Project plan for 2027–2030, Budget summary) Additional data needed for the fascicle Outcomes and Outputs UN system coordination Budget narrative Background Section Describe the issue the project intends to address, including broader context. Refer to human rights-based approach, gender, and disability inclusion. Clearly articulate demand for support from Member States (requests, needs assessments, resolutions). Provide a tentative list of potential target countries, if known. Explain the connection to the work of the implementing entity and its comparative advantages. Fascicle Note Title: Concise, positive, and thematic, including geographical scope. Implementing entity and partners: List all DA entities involved, starting with the lead entity. Relationship to SDG targets: List relevant SDG targets (max. 10). Objective: State the intended goal in one sentence, referencing beneficiaries, scope, and focus. Project plan: Paragraph 1: Context and trigger (describe the problem and what prompted the project). Paragraph 2: Explain the project, including the number of countries, regions, and actions enabled. Paragraph 3: Expected progress, starting with “This work is expected to contribute to (objective), which would be demonstrated by (evidence of progress).” Budget summary: Use the required table format, figures in thousands of USD, do not delete any categories. Additional Data Needed for the Fascicle Complete tables on support for countries with special needs (SIDS, LLDCs, LDCs), regions, SDGs, partnerships, consultancy requirements, and deliverables. Outcomes and Outputs Outcomes: Describe expected changes achievable within the project timeframe and budget. Outputs: List specific actions, products, or reports needed to achieve outcomes. Use the format: OC1, OP1.1, OP1.2, etc. UN System Coordination Elaborate on coordination/implementation with Resident Coordinator Offices (RCOs) and UN Country Teams. Provide a table with target countries and planned RCO involvement. Briefly describe partnerships, including roles of DA and non-DA entities. Budget Narrative Provide detailed justification for each budget category (Other staff costs, Consultants, Travel, Contractual services, General operating expenses, Grants and contributions). Use the required format and ensure figures add up to the total. Quality Assurance Before submission, conduct an internal review using the provided checklist to ensure all sections are complete, accurate, and follow the required format. Timeline Be aware of key deadlines for submission, review, and approval as outlined in the guidelines. Challenges and Tips: Ensure demand is clearly demonstrated and the logic underpinning the project is sound. Focus on countries with special needs (LDCs, LLDCs, SIDS) and consider joint projects for additional funding. Follow the format strictly to reduce editing and facilitate review. Sources: ​T19 Concept Note Guidelines.docx​ ​T19 Concept Note Template.docx​ ​T19 Concept Note Review Checklist for DA Focal Points.docx​ Confidence: Very High | F93: yes | H93: Very High | I93: YEs | J93: 46190 | K93: 47 seconds | M93: User Inquiry greeting classifier sets isGreeting=false because the input includes a substantive question. The input continues to Intent and routes to Formulate Response DA with funding_stream=DA and topic_area=project_planning_design. | N93: 2026-05-28
A94: Exit Cidy flow command - exact phrase [Exit Flow] | B94: =_xlfn.TEXTBEFORE(_xlfn.TEXTAFTER(A94,"[",-1),"]") -> Exit Flow | C94: exit Cidy flow | D94: Successful | M94: Exit Cidy Flow switches Global.cidyMode to open, sends the outside structured Cidy flow message, and continues future user messages through open conversation mode without routing the command to Intent. | N94: 2026-05-31
A95: Exit Cidy flow command - Cindy typo [Exit Flow] | B95: =_xlfn.TEXTBEFORE(_xlfn.TEXTAFTER(A95,"[",-1),"]") -> Exit Flow | C95: exit Cindy flow | D95: Successful | M95: Exit Cidy Flow recognizes the Cindy typo, switches Global.cidyMode to open, sends the outside structured Cidy flow message, and does not route the command as an About Cidy knowledge question. | N95: 2026-05-31
A96: Return to Cidy rescue path [Exit Flow] | B96: =_xlfn.TEXTBEFORE(_xlfn.TEXTAFTER(A96,"[",-1),"]") -> Exit Flow | C96: Back to Cidy flow | D96: Successful | M96: Return to Cidy topic cancels other topics, clears active Cidy state, asks for a fresh substantive question, stores it as Global.userQuestion, and routes that captured question to Intent_c8W. | N96: 2026-05-28
A97: Happy path - Country Data active projects by country [Country Data] | B97: =_xlfn.TEXTBEFORE(_xlfn.TEXTAFTER(A97,"[",-1),"]") -> Country Data | C97: Which projects are currently active in Kenya? | M97: Routes directly to Formulate Response Programme Development with knowledge_domain=programme_development, funding_stream=UNCLEAR, topic_area=country_data, requires_clarification=No. Response uses the Country Data folder for active projects by country. | N97: 2026-06-02
A98: Regression - broad country work routes to Country Data [Country Data] | B98: =_xlfn.TEXTBEFORE(_xlfn.TEXTAFTER(A98,"[",-1),"]") -> Country Data | C98: list all work in argentina | M98: Routes directly to Formulate Response Programme Development with knowledge_domain=programme_development, funding_stream=UNCLEAR, topic_area=country_data, requires_clarification=No. Broad country work wording should use Country Data, not project evaluations, unless the user explicitly asks for evaluations. | N98: 2026-06-08
A99: Happy path - Country Data proposal year list [Country Data] | B99: =_xlfn.TEXTBEFORE(_xlfn.TEXTAFTER(A99,"[",-1),"]") -> Country Data | C99: I'd like to see 2026 proposals. | M99: Routes directly to Formulate Response Programme Development with knowledge_domain=programme_development, funding_stream=UNCLEAR, topic_area=country_data, requires_clarification=No. Response uses the Country Data folder for proposal-year filtering. | N99: 2026-06-02
A100: Happy path - Country Data LDC activity count [Country Data] | B100: =_xlfn.TEXTBEFORE(_xlfn.TEXTAFTER(A100,"[",-1),"]") -> Country Data | C100: How many activities in 2025 targeted LDCs? | M100: Routes directly to Formulate Response Programme Development with knowledge_domain=programme_development, funding_stream=UNCLEAR, topic_area=country_data, requires_clarification=No. Response uses the Country Data folder for activity counts by year and LDC target group. | N100: 2026-06-02
